Workbook

Sheet Sheet10
A1: TAG NUMBER | B1: Previous Company ID | D1: Category | E1: Location | F1: Description | G1: Serial Number or IMEI | H1: Additional Accessories | I1: Department
A2: MON001 | B2: - | C2: Monitor | D2: Moeketse Kuenane | E2: O&M Section | F2: Dell 24 FHD | G2: CN-ORGF30-WSLOO-14Q-HL1L-A04 | H2: HDMI Cable | I2: Operations and Maintenance
A3: MON002 | B3: 0081 | C3: Monitor | D3: Rasekeiti Mohlomi | E3: O&M Section | F3: Dell 24 FHD | G3: 406SAAB0B968 | H3: HDMI Cable Ethernet cable | I3: Operations and Maintenance
A4: MON003 | B4: 0420 | C4: Monitor | D4: Neo Serobanyane | E4: O&M Section | F4: Dell 24 FHD | G4: 038969100343082020H | H4: HDMI Cable Ethernet cable | I4: Operations and Maintenance
A5: MON004 | B5: - | C5: Monitor | D5: Matthew Orosz | E5: EHS Section | F5: Dell 24 FHD | G5: CN-0XXCGP-TV200-26H-DCSV-A03 | I5: -
A6: MON005 | B6: 0381-B | C6: Monitor | D6: Jonase Nthunya | E6: EHS Section | F6: Viewsonic | G6: V86184340487 | I6: EHS
A7: MON006 | B7: - | C7: Monitor | D7: Tlhokomelo Kikine | E7: EE and IT Area | F7: Dell 24 FHD | G7: CN-0WWWVVK-B0Z00-15S-0PAB-A00 | H7: HDMI Cable | I7: IT
A8: MON007 | B8: - | C8: Monitor | D8: Tumisang Mathaba | E8: Production Area | F8: Dell 24 FHD | I8: Production
A9: MON008 | B9: EE08 | C9: Monitor | D9: Rantsane Tsosane | E9: Procurement Section | F9: Samsung | G9: 4L24H7BR401226Z | H9: Keyboard,VGA,Mouse Mounted Multi Plug, Ethernet Cable | I9: Procurement
A10: MON009 | B10: - | C10: Monitor | D10: Mlanjeni Tikiso | E10: PM Section | F10: Samsung | G10: 4L24H7BR401267M | I10: PM
A11: MON010 | B11: EE06 | C11: Monitor | D11: lap | E11: PM Section | F11: Philips | G11: XVDA2116003944 | I11: PM
A12: MON011 | B12: EE09 | C12: Monitor | D12: Teboho Molantoa | E12: PM Section | F12: Viewsonic | G12: V86184340506 | I12: PM
A13: MON012 | B13: 0423-D | C13: Monitor | D13: Katleho Pule | E13: PM Section | F13: Telefunken | G13: 039868-102156-012021J | I13: PM
A14: MON013 | B14: AD003 | C14: Monitor | D14: Moliehi Lepheane | E14: Admin and Finance | F14: Telefunken | G14: 5C7A53BD-C438-46F3-A042-0EBC98F4743E | I14: Admin
A15: MON014 | B15: AD002 | C15: Monitor | D15: Refiloe Ramalefane | E15: Admin and Finance | F15: Telefunken | G15: F1782735-54E5-469A-92C9-22A543C566E8 | I15: Finance
A16: MON015 | B16: AD001 | C16: Monitor | D16: Palama Kelepa | E16: Admin and Finance | F16: Dell 24 FHD | G16: CN-0WWVVK-BOZ00-158-0B2B-A00 | I16: Finance
A17: MON016 | B17: EHS-05 | C17: Monitor | D17: Mojabeng Sonopo | E17: EE and IT Area | F17: Dell 24 FHD | G17: CN-0WWVVK-BOZ00-155-0P88-A00 | I17: PM
A18: MON017 | B18: EE001 | C18: Monitor | D18: Josias Molomo | E18: EE and IT Area | F18: Dell 24 FHD | G18: CN-0RGF30-WSL00-14Q-HLNL-A04 | I18: EE
A19: MON018 | B19: - | C19: Monitor | D19: Motlatsi Manka | E19: EE and IT Area | F19: Dell 24 FHD | G19: CN-011PWC-WSL00-1AP-AQVP-A04 | I19: EE
A20: MON019 | B20: EE06 | C20: Monitor | D20: Thabang Hatlane | E20: EE and IT Area | F20: Dell 24 FHD | G20: CN-0WWVVK-BOZ00-155-2C6B-A00 | I20: EE
A21: MON020 | B21: EE05 | C21: Monitor | D21: Motebang Lekhooana | E21: EE and IT Area | F21: Dell 24 FHD | G21: CN-0RGF30-WSL00-14Q-HL1L-A04 | I21: IT
... A25: MON024 | B25: EE07 | C25: Monitor | D25: Lichaba West | E25: Production Area | F25: Dell 24 FHD | G25: CN-0WWVVK-BOZ00-15S-06AB-A00 | I25: Production
A26: MON025 | B26: EE02 | C26: Monitor | D26: - | I26: Production
A27: MON026 | B27: P001 | C27: Monitor | D27: Production | E27: Production Area | F27: Telefucken | I27: Production
A28: MON027 | B28: - | C28: Monitor | D28: Thabo Monoto | E28: EE and IT Area | F28: Dell 24 FHD | G28: CN-011PWC-WSL00-1B5-379B-A05 | I28: EE
A29: MON028 | B29: - | C29: Monitor | D29: unassigned | E29: EE and IT Area | F29: Dell 24 FHD | G29: CN-0XXCGP-TV200-26H-057V-A03
A30: MON029 | B30: - | C30: Monitor | D30: Kananelo Mokobori | E30: Production Area | F30: Dell 24 FHD | G30: CN-0XXCGP-TV200-26H-094V-A03
A31: MON030 | B31: - | C31: Monitor | D31: Tumelo Tshabalala | E31: EE and IT Area | F31: Dell 24 FHD | G31: CN-0XXCGP-TV200-26H-055V-A03
A32: MON031 | B32: - | C32: Monitor | D32: unassigned | E32: EE and IT Area | F32: Dell 24 FHD | G32: CN-0XXCGP-TV200-26H-08MV-A03
A33: MON032 | B33: - | C33: Monitor | D33: Operations and Maintenance | E33: O&M Section | F33: AIWA | H33: HDMI | I33: O&M
A34: MON033 | B34: - | C34: Monitor | D34: Operations and Maintenance | E34: O&M Section | F34: AIWA | I34: O&M
A35: MON034 | B35: - | C35: Monitor | D35: Operations and Maintenance | E35: O&M Section | F35: AIWA | I35: O&M
A36: MON035 | B36: - | C36: Monitor | D36: CCTV | E36: Admin and Finance | I36: Finance
A37: MON036 | B37: - | C37: Monitor | D37: unassigned | E37: Dead | F37: Dell 24 FHD
A38: MON037 | B38: - | C38: Monitor | D38: unassigned | E38: Dead | F38: Telefucken
A39: MON038 | B39: - | C39: Monitor | D39: Keketso Mosenene | E39: finance | F39: meccer | I39: finance
A45: CPU001 | B45: 0444 | C45: CPU | D45: Operations and Maintenance | E45: O&M Section | F45: HP | I45: O&M
A46: CPU002 | B46: CP04 | C46: CPU | D46: Operations and Maintenance | E46: O&M Section | F46: HP | G46: 2UA2490668V | I46: O&M
A47: CPU003 | B47: CP02 | C47: CPU | D47: Lineo Mosoenyane | E47: Procurement Section | F47: HP | G47: MXL33922C46 | I47: Procurement
A48: CPU004 | B48: D-008 | C48: CPU | D48: Rantsane Tsosane | E48: Procurement Section | F48: HP | G48: 2UA3090QN4 | I48: Procurement
A49: CPU005 | B49: D-001 | C49: CPU | D49: Morongwa Saku | E49: PM Section | F49: HP | G49: MXL3160RFN | I49: PM
A50: CPU006 | B50: D-009 | C50: CPU | D50: Teboho Molantoa | E50: PM Section | F50: HP | G50: MXL3110Y3P | I50: PM
A51: CPU007 | B51: D-004 | C51: CPU | D51: Moliehi Lepheane | E51: Admin and Finance | F51: HP | G51: MXL2351QG2 | I51: Finance
A52: CPU008 | B52: D-005/0423-A | C52: CPU | D52: Refiloe Ramalefane | E52: Admin and Finance | F52: HP | G52: 2UA2380RMP | I52: Finance
A53: CPU009 | B53: CP01 | C53: CPU | D53: Mojabeng Sonopo | E53: EE and IT Area | F53: HP | G53: MXL2501N43 | I53: PM
A54: CPU010 | B54: P001/D-007 | C54: CPU | D54: Production | E54: Production Area | F54: HP | G54: 2UA32521R5 | I54: Production
A55: CPU011 | B55: CP03 | C55: CPU | D55: Tumisang Mathaba | E55: Production Area | F55: HP | G55: MXL31601BY | I55: Production
A56: CPU012 | B56: 001EE/0423-D | C56: CPU | D56: Lichaba West | E56: Production Area | F56: HP | G56: MXL3340HZD | I56: Engineering
A57: CPU013 | B57: 0445/D006/FF 01 | C57: CPU | D57: Ralefaso | E57: Production Area | F57: HP | G57: 2UA23602PV | I57: Production
A58: CPU014 | B58: D002 | C58: CPU | D58: Deon Du Preez | E58: Production Area | F58: HP | G58: 2UA3231969 | I58: Production
A59: CPU015 | C59: CPU | D59: Deon Du Preez | E59: Reported Stolen
A60: CPU016 | B60: - | C60: CPU | D60: IT LOCKER | E60: Keketso Mosenene | F60: HP | G60: 2UA3060GGW | I60: Finance
A61: CPU017 | B61: c | C61: CPU | D61: Katleho Pule | E61: IT LOCKER | F61: HP | G61: 2UA3090QQ7
C62: CPU | D62: IT LOCKER | E62: IT LOCKER | F62: HP
C63: CPU | D63: IT LOCKER | E63: IT LOCKER | F63: HP
A69: MOU001 | B69: 0423-D | C69: Mouse | D69: Neo Serobanyane | E69: O&M Section | G69: -
A70: MOU002 | B70: LOG04 | C70: Mouse | D70: MON033 | E70: O&M Section | F70: Logitech | G70: 2045HSO05VBV8
A71: MOU003 | B71: - | C71: Mouse | D71: - | E71: IT Locker | F71: BTO | G71: -
A72: MOU004 | B72: - | C72: Mouse | D72: - | E72: EE Locker | F72: Volkano | G72: -
A73: MOU005 | B73: - | C73: Mouse | D73: Operations and Maintenance | E73: O&M Section | F73: HP | G73: -
A74: MOU006 | B74: - | C74: Mouse | D74: MON32 | E74: O&M Section | F74: Logitech | G74: 2119LZX5UVA8
A75: MOU007 | B75: - | C75: Mouse | D75: Tumisang Mathaba | E75: Production Area | F75: - | G75: -
A76: mou008 | B76: tag clash | C76: Mouse | D76: Katleho Pule | E76: PM Section
A77: MOU008 | B77: - | C77: Mouse | D77: Keketso Mosenene | E77: Finance | F77: Volkano | G77: -
A78: MOU009 | B78: - | C78: Mouse | D78: Jonase Nthunya | E78: EHS Section | F78: - | G78: -
A79: MOU010 | B79: - | C79: Mouse | D79: Lineo Mosoenyane | E79: Procurement Section | F79: Volkano | G79: -
A80: MOU011 | B80: - | C80: Mouse | D80: Rantsane Tsosane | E80: Procurement Section | F80: Logitech | G80: 2133HS0A3BR8
A81: MOU012 | B81: - | C81: Mouse | D81: Morongwa Saku | E81: PM Section | F81: Volkano | G81: -
A82: MOU013 | B82: - | C82: Mouse | D82: Mamoritshoane Tlaba | E82: PM Section | F82: Utra Link | G82: 202103703000
A83: MOU014 | B83: - | C83: Mouse | D83: Moliehi Lepheane | E83: Admin and Finance | F83: Microsoft | G83: R20114004
A84: MOU015 | B84: 0423-A | C84: Mouse | D84: Refiloe Ramalefane | E84: Admin and Finance | F84: Volkano | G84: -
A85: MOU016 | B85: LOG01 | C85: Mouse | D85: Mojabeng Sonopo | E85: EE and IT Area | F85: Logitech | G85: 2125HSO4PYF8
A86: MOU017 | B86: 009 | C86: Mouse | D86: Josias Molomo | E86: EE and IT Area | G86: -
A87: MOU018 | B87: - | C87: Mouse | D87: Thabang Hatlane | E87: EE and IT Area | G87: 2133H50835Z8
A88: MOU019 | B88: - | C88: Mouse | D88: Motebang Lekhooana | E88: EE and IT Area | F88: Astrum | G88: -
A89: MOU020 | B89: - | C89: Mouse | D89: Thabo Monoto | E89: EE and IT Area | F89: Logitech | G89: 2119LZX5UUV6
A90: MOU021 | B90: LOG02 | C90: Mouse | D90: Thabo Monoto | E90: EE and IT Area | F90: Logitech | G90: 2115HS07BET8
A91: MOU022 | B91: 0423-C | C91: Mouse | D91: Production | E91: Production Area | F91: Volkano
A92: MOU023 | B92: EE07 | C92: Mouse | D92: Lichaba West | E92: Production Area | F92: Logitech | G92: 2133HS0A3DD8
A93: MOU024 | C93: Mouse | D93: Thabo Monoto | E93: Production Area | F93: RCT
A94: MOU025 | B94: - | C94: Mouse | D94: Production | E94: Production Area | F94: Volkano | G94: -
A95: MOU026 | B95: - | C95: Mouse | D95: Deon Du Preez | E95: Production Area | F95: Volkano | G95: -
A96: MOU027 | B96: - | C96: Mouse | D96: Lefa Seshemane | E96: retivulation | F96: Gigabyte | G96: 212615003807
A97: MOU028 | B97: - | C97: Mouse | D97: Taole Letseka | E97: IT LOCKER | F97: Gigabyte | G97: 212615004177
A98: MOU029 | C98: Mouse | D98: Mokoatle Mokoatle | E98: IT LOCKER | F98: Logitech | G98: 2134HS06YYT8
A99: MOU030 | B99: - | C99: Mouse | D99: Mokhethi Komete | E99: IT LOCKER | F99: Volkano | G99: -
A100: MOU031 | B100: - | C100: Mouse | D100: Mahlela RET | E100: RET | F100: Gigabyte
A101: MOU032 | B101: - | C101: Mouse | D101: Officer gate | E101: - | F101: -
A102: MOU033 | B102: - | C102: Mouse | D102: Rethabile Lempheane | E102: O&M Section | F102: -
A103: MOU034 | B103: - | C103: Mouse | D103: Mojabeng Sonopo | E103: pm Section | F103: -
A104: MOU035 | B104: - | C104: Mouse | D104: - | E104: IT LOCKER | F104: logictech mouse | G104: 2134HS06YYT8
A105: MOU036 | B105: - | C105: Mouse | D105: - | E105: IT LOCKER | F105: logictech mouse
A106: MOU037 | B106: - | C106: Mouse | D106: - | E106: IT LOCKER | F106: mouse
A107: MOU038 | B107: - | C107: Mouse | D107: - | E107: IT LOCKER | F107: mouse
A108: MOU039 | B108: - | C108: Mouse | D108: Kananelo Mokobori | E108: Production Area | F108: mouse
A109: MOU040 | B109: - | C109: Mouse | D109: - | E109: IT LOCKER | F109: mouse
A110: MOU041 | B110: - | C110: Mouse | D110: - | E110: IT LOCKER | F110: mouse
A111: MOU042 | B111: - | C111: Mouse | D111: - | E111: IT LOCKER | F111: mouse
A112: MOU043 | B112: - | C112: Mouse | D112: - | E112: IT LOCKER | F112: mouse
A113: MOU044 | B113: EE03 | C113: Mouse | D113: - | E113: IT LOCKER | F113: mouse
...

Sheet Inventory
A1: Timestamp | B1: Company ID | C1: State | D1: Phone Number | E1: Category | F1: Assigned to (Full names of assignee) | G1: Quantity | H1: Location | I1: Description | J1: Serial Number | K1: Device Setup(any software/ application installed) | L1: Additional Accessories | M1: Department
B3: OnM Deparment Desktop | E3: Desktop | F3: OnM Deparment Desktop | G3: 1 | H3: OnM | I3: Screen Displays | J3: D-003 | K3: Microsoft Office, Chrome, PDF Reader, Google Earth Pro | L3: mouse, Keyboard, 3 Monitors and their Remotes, 2 Display Devices, WiFi Dongle, Multiplug | M3: Operations and Maintenance
B4: LOG01 | E4: Mouse | F4: Mojabeng Sonopo | G4: 1 | H4: EE Area | I4: Logitech Mouse | J4: 2125HSO4PYF8 | L4: Mouse Pad | M4: EE
B5: LOG02 | E5: Mouse | F5: Thabo Monoto | G5: 1 | H5: EE Locker | I5: Logitech Mouse | J5: 2115HS07BET8 | K5: - | M5: EE
B6: LOG03 | E6: Mouse | F6: Rasekeiti Mohlomi | G6: 1 | H6: EE Locker | I6: Logitech Mouse | J6: 2048HS018YP8 | K6: - | M6: EE
B7: LOG04 | E7: Mouse | F7: - | G7: 1 | H7: EE Locker | I7: Logitech mouse | J7: 2045HSO05VBV8 | K7: - | L7: - | M7: EE
B8: CHR01 | E8: Charger | F8: Mojabeng Sonopo | G8: 1 | H8: EE Locker | I8: HP charger | J8: WCQAAAOC1R5YICZ | K8: - | L8: - | M8: EE
B9: CHR02 | E9: charger | F9: - | G9: 1 | H9: EE Locker | I9: HP charger | J9: WCQAAOC1R4SFX9 | K9: - | L9: - | M9: EE
B10: CHR03 | E10: charger | F10: Rasekeiti Mohlomi | G10: 1 | H10: EE Locker | I10: HP charger | J10: WBBXR0ALAZY6VS | K10: - | L10: - | M10: EE
B11: CHRO4 | E11: charger | F11: - | G11: 1 | H11: EE Locker | I11: HP charger | J11: WCQAAOC1R8HD0H | K11: - | L11: - | M11: EE
B12: KB01 | E12: keyboard | F12: Mojabeng Sonopo | G12: 1 | H12: EE Locker | I12: Keyboard | K12: - | L12: - | M12: EE
B13: KB02 | E13: keyboard | F13: Thabo Monoto | G13: 1 | H13: EE locker | I13: keyboard | K13: - | L13: - | M13: EE
B14: KB03 | E14: Keyboard | F14: Rasekeiti Mohlomi | G14: 1 | H14: EE Locker | I14: keyboard | K14: - | L14: - | M14: EE
B15: KB04 | E15: Keyboard | F15: - | G15: 1 | H15: EE locker | I15: keyboard | K15: - | L15: - | M15: EE
B16: CP01 | E16: CPU | F16: Mojabeng Sonopo | G16: 1 | H16: EE locker | I16: HP | J16: MXL2501N43 | K16: - | L16: Wifi Adapter Display to HDMI | M16: EE
B17: CP02 | E17: CPU | F17: Lineo | G17: 1 | H17: Procument | I17: HP CPU | J17: MXL3392C46 | K17: - | L17: Display to HDMI Keyboard(KB02) Wifi Adapter Extension Cord Multi Plug Mouse (LOG02) Universal Adapter | M17: Procurement
B18: CP03 | E18: Desktop | F18: - | G18: 1 | H18: EE locker | I18: Desktop (cpu) | J18: MXL31601BY | K18: - | L18: - | M18: EE
B19: CP04 | E19: Desktop | F19: - | G19: 1 | H19: EE Locker | I19: Desktop (cpu) | J19: 2UA2490668V | K19: - | L19: - | M19: EE
B20: LDS00 | E20: Loudspeaker | F20: - | G20: 1 | H20: EE locker | I20: loudspeaker | J20: - | K20: - | L20: - | M20: EE
B21: RBP00 | E21: Raspberry pie | F21: Thabo Monoto | G21: 1 | H21: EE locker | I21: Raspberry pie | J21: 2019AJI0494 | K21: - | L21: - | M21: EE
B22: SML001 | E22: Smart Locker | F22: - | G22: 1 | H22: EE locker | I22: smart locker | J22: - | K22: - | L22: - | M22: Facilities
B23: SML002 | E23: Smart Locker | F23: - | G23: 1 | H23: EE Locker | I23: smart locker | J23: - | K23: - | L23: - | M23: Facilities
B24: SML003 | E24: smart locker | F24: - | G24: 1 | H24: EE locker | I24: smart locker | J24: - | K24: - | L24: - | M24: Facilities
B25: SML004 | E25: Smart locker | F25: - | G25: 1 | H25: EE locker | I25: smart locker | J25: - | K25: - | L25: - | M25: Facilities
B26: SML 005 | E26: smart locker | F26: - | G26: 1 | H26: EE locker | I26: smart locker | J26: - | K26: - | L26: - | M26: Facilities
B27: PMP001 | E27: car pump | F27: - | G27: 1 | H27: EE locker | I27: car pump | J27: - | K27: - | L27: - | M27: Fleet
B28: BULB001 | E28: KS Turn replacement bulb | F28: - | G28: 2 | H28: EE locker | I28: KS Turn replacement bulb | J28: - | K28: - | L28: - | M28: EE
B29: Untagged/None
B30: Surf -1 | C30: =IF(B:B='Check in'!B:B,"Usable",IF('Check in'!D:D="Good Condition","Usable","Not Usable")) -> Not Usable | D30: 57253337 | E30: Phone | F30: Lost | G30: 1 | H30: Surf -1 | J30: 359137090447944 | M30: Fleet
B31: Main | C31: =IF(B:B='Check in'!B:B,"Usable",IF('Check in'!D:D="Good Condition","Usable","Not Usable")) -> Not Usable | D31: 57755403 | E31: Phone | F31: Phoka Raphoka | G31: 1 | H31: HQ | J31: 359137090448892 | L31: Charger | M31: Procurement
B32: X-trail Phone | C32: =IF(AND('Check in'!B:B=B32,'Check in'!D:D="Good Condition"),"Not Usable","Usable") -> Usable | D32: 50002953 | E32: Phone | F32: Replaced | G32: 1 | H32: X-trail | J32: 357441100338545 | M32: Fleet
B33: Truck 36 Phone | C33: =IF(AND('Check in'!B:B=B33,'Check in'!D:D="Good Condition"),"Not Usable","Usable") -> Usable | D33: 57517692 | E33: Phone | F33: Replaced | G33: 1 | H33: Truck 36 Phone | J33: 357441100288138 | M33: Fleet
B34: SMS gateway | C34: =IF(AND('Check in'!B:B=B34,'Check in'!D:D="Good Condition"),"Not Usable","Usable") -> Usable | D34: 50329017 | E34: Phone | F34: EHS Department | G34: 1 | H34: O&M Department | I34: Samsung A02,Blue,6.5",32GB | J34: 867173041276079 | M34: O&M
B35: Dev & Test Phone | C35: =IF(AND('Check in'!B:B=B35,'Check in'!D:D="Good Condition"),"Not Usable","Usable") -> Usable | D35: 63557950 | E35: Phone | F35: EE Department | G35: 1 | H35: IT Locker | J35: 864931055950225
B36: Makebe Field Site 0363 | C36: =IF(AND('Check in'!B:B=B36,'Check in'!D:D="Good Condition"),"Usable","Not Usable") -> Not Usable | D36: 59436506 | E36: Phone | F36: Teboho Noko | G36: 1 | H36: Makebe Field Site 0363 | J36: 355622107185433 | M36: Reticulation
B37: Survey Phone 0369 | C37: =IF(AND('Check in'!B:B=B37,'Check in'!D:D="Good Condition"),"Usable","Not Usable") -> Not Usable | D37: 56434364 | E37: Phone | F37: Broken | G37: 1 | H37: IT Locker | I37: Azumi v5+, 5.0" Screen Broken ,replacement parts currently unavailable. | J37: 357441100355838 | M37: EHS
B38: Survey Phone 0370 | D38: 58488198 | E38: Phone | F38: Replaced | G38: 1 | H38: Survey Phone 0370 | J38: 357441100356166
B39: Pajero | C39: =IF(AND('Check in'!B:B=B39,'Check in'!D:D="Good Condition"),"Usable","Not Usable") -> Not Usable | D39: 56660005 | E39: Phone | F39: Fleet Department | G39: 1 | H39: Pajero | J39: 358846169697376 | M39: Fleet
B40: Surf -2 0373 | C40: =IF(AND('Check in'!B:B=B40,'Check in'!D:D="Good Condition"),"Usable","Not Usable") -> Not Usable | D40: 58757576 | E40: Phone | F40: Fleet Department | G40: 1 | H40: IT Locker | J40: 482990508507030510 | M40: Fleet
B41: Customer Support | C41: =IF(AND('Check in'!B:B=B41,'Check in'!D:D="Good Condition"),"Usable","Not Usable") -> Not Usable | D41: 58342168 | E41: Phone | F41: O&M Department | G41: 1 | H41: O&M Department | J41: 511008240007080
C42: Not Usable | D42: 58808402 | E42: Phone | F42: Manneuoa Molefi | G42: 1 | H42: HR Department | I42: Hisense | J42: SGKS605H21103100962 | M42: HR Department
B43: Com 01 | C43: =IF(AND('Check in'!B:B=B43,'Check in'!D:D="Good Condition"),"Usable","Not Usable") -> Not Usable | D43: 56601825 | E43: Phone | F43: Tumelo Makhetha | G43: 1 | H43: PM Department | I43: Samsung A02,Blue,6.5",32GB | J43: 351813381603563 | K43: WhatsApp Google Account | L43: Charger , Headsets Screen Protector Phone Case | M43: Project Management
B44: Com 02 | C44: =IF(AND('Check in'!B:B=B44,'Check in'!D:D="Good Condition"),"Usable","Not Usable") -> Not Usable | D44: 56601826 | E44: Phone | F44: Mongali Tlali | G44: 1 | H44: PM Department | I44: Samsung A02,Blue,6.5",32GB | J44: 351813381607432 | K44: WhatsApp Google Account | L44: Charger , Headsets Screen Protector Phone Case | M44: Project Management
B45: Com 03 | C45: =IF(AND('Check in'!B:B=B45,'Check in'!D:D="Good Condition"),"Usable","Not Usable") -> Not Usable | D45: 56601824 | E45: Phone | F45: Phoka Raphoka | G45: 1 | H45: Procurement Department | I45: Samsung A02,Blue,6.5",32GB | J45: 351813381636993 | K45: WhatsApp Google Account | L45: Charger , Headsets | M45: Project Management
B46: Com 04 | C46: =IF(AND('Check in'!B:B=B46,'Check in'!D:D="Good Condition"),"Usable","Not Usable") -> Not Usable | D46: 56601846 | E46: Phone | F46: Tumelo Makhetha | G46: 1 | H46: Mashai,Taung | I46: Samsung A02,Blue,6.5",32GB | J46: 351813381605006 | K46: WhatsApp Google Account | L46: Charger , Headsets,screen protector,phone cover | M46: Project Management
B47: Com 05 | C47: =IF(AND('Check in'!B:B=B47,'Check in'!D:D="Good Condition"),"Usable","Not Usable") -> Not Usable | D47: 56601829 | E47: Phone | F47: Tumelo Makhetha | G47: 1 | H47: Mashai, St. Theresa | I47: Samsung A02,Blue,6.5",32GB | J47: 351813381595207 | K47: WhatsApp Google Account | L47: Charger , Headsets,screen protector,phone cover | M47: Project Management
B48: Com 06 | C48: =IF(AND('Check in'!B:B=B48,'Check in'!D:D="Good Condition"),"Usable","Not Usable") -> Not Usable | D48: 56601830 | E48: Phone | F48: Tumelo Makhetha | G48: 1 | H48: Sehonghong,Sekhaupane | I48: Samsung A02,Blue,6.5",32GB | J48: 351813381626242 | K48: WhatsApp Google Account | L48: Charger , Headsets | M48: Project Management
B49: Com 07 | C49: =IF(AND('Check in'!B:B=B49,'Check in'!D:D="Good Condition"),"Usable","Not Usable") -> Not Usable | D49: 56601831 | E49: Phone | F49: Tumelo Makhetha | G49: 1 | H49: Mashai,Ha Boomo | I49: Samsung A02,Blue,6.5",32GB | J49: 351813381603698 | K49: WhatsApp Google Account | L49: Charger , Headsets,screen protector,phone cover | M49: Project Management
B50: Com 08 | C50: =IF(AND('Check in'!B:B=B50,'Check in'!D:D="Good Condition"),"Usable","Not Usable") -> Not Usable | D50: 56601832 | E50: Phone | F50: Tumelo Makhetha | G50: 1 | H50: Mashai,Moreneng | I50: Samsung A02,Blue,6.5",32GB | J50: 351813381601492 | K50: WhatsApp Google Account | L50: Charger , Headsets,screen protector,phone cover | M50: Project Management
B51: Com 09 | C51: =IF(AND('Check in'!B:B=B51,'Check in'!D:D="Good Condition"),"Usable","Not Usable") -> Not Usable | D51: 56601801 | E51: Phone | G51: 1 | H51: IT Locker | I51: Samsung A02,Blue,6.5",32GB | J51: 351813381609917 | K51: WhatsApp Google Account | L51: Charger | M51: Project Management
B52: Com 10 | C52: =IF(AND('Check in'!B:B=B52,'Check in'!D:D="Good Condition"),"Usable","Not Usable") -> Not Usable | D52: 50329017 | E52: Phone | F52: O&M | G52: 1 | H52: O&M Department | I52: Samsung A02,Blue,6.5",32GB | J52: 351813381599415 | K52: WhatsApp Google Account | L52: Charger , Headsets | M52: Project Management
B53: Com 11 | C53: =IF(AND('Check in'!B:B=B53,'Check in'!D:D="Good Condition"),"Usable","Not Usable") -> Not Usable | D53: 56601836 | E53: Phone | F53: Tumelo Makhetha | G53: 1 | H53: Sehonghong,Lebung | I53: Samsung A02,Blue,6.5",32GB | J53: 351813381601310 | K53: WhatsApp Google Account | L53: Charger , Headsets | M53: Project Management
B54: Com 12 | C54: =IF(AND('Check in'!B:B=B54,'Check in'!D:D="Good Condition"),"Usable","Not Usable") -> Not Usable | D54: 56601837 | E54: Phone | F54: Tumelo Makhetha | G54: 1 | H54: Sehonghong, Seruting | I54: Samsung A02,Blue,6.5",32GB | J54: 351813381572792 | K54: WhatsApp Google Account | L54: Charger , Headsets | M54: Project Management
B55: Com 13 | C55: =IF(AND('Check in'!B:B=B55,'Check in'!D:D="Good Condition"),"Usable","Not Usable") -> Not Usable | D55: 56601839 | E55: Phone | F55: Tumelo Makhetha | G55: 1 | H55: Sehonghong,Tlokoeng ha Mofao | I55: Samsung A02,Blue,6.5",32GB | J55: 351813381596627 | K55: WhatsApp Google Account | L55: Charger , Headsets | M55: Project Management
B56: Com 14 | C56: =IF(AND('Check in'!B:B=B56,'Check in'!D:D="Good Condition"),"Usable","Not Usable") -> Not Usable | D56: 56601838 | E56: Phone | F56: Tumelo Makhetha | G56: 1 | H56: Sehonghong,Ha Poko | I56: Samsung A02,Blue,6.5",32GB | J56: 351813381594911 | K56: WhatsApp Google Account | L56: Charger , Headsets | M56: Project Management
B57: Com 15 | C57: =IF(AND('Check in'!B:B=B57,'Check in'!D:D="Good Condition"),"Usable","Not Usable") -> Not Usable | D57: 56601841 | E57: Phone | F57: Tumelo Makhetha | G57: 1 | H57: Sehonghong,Aupolasi | I57: Samsung A02,Blue,6.5",32GB | J57: 351813381632711 | K57: WhatsApp Google Account | L57: Charger , Headsets | M57: Project Management
B58: Com 16 | C58: =IF(AND('Check in'!B:B=B58,'Check in'!D:D="Good Condition"),"Usable","Not Usable") -> Not Usable | D58: 56601842 | E58: Phone | F58: Tumelo Makhetha | G58: 1 | H58: Sehonghong,Ha Molaoa | I58: Samsung A02,Blue,6.5",32GB | J58: 351813381608703 | K58: WhatsApp Google Account | L58: Charger , Headsets | M58: Project Management
B59: Com 17 | C59: =IF(AND('Check in'!B:B=B59,'Check in'!D:D="Good Condition"),"Usable","Not Usable") -> Not Usable | D59: 56601844 | E59: Phone | F59: Tumelo Makhetha | G59: 1 | H59: Tlhanyaku In Xtrail | I59: Samsung A02,Blue,6.5",32GB | J59: 351813381632497 | K59: WhatsApp Google Account | L59: Charger , Headsets | M59: Fleet
B60: Com 18 | C60: =IF(AND('Check in'!B:B=B60,'Check in'!D:D="Good Condition"),"Usable","Not Usable") -> Not Usable | D60: 56601822 | E60: Phone | F60: Tumelo Makhetha | G60: 1 | H60: Sehonghong,Ha Sekhaupane | I60: Samsung A02,Blue,6.5",32GB | J60: 351813381600932 | K60: WhatsApp Google Account | L60: Charger , Headsets | M60: Project Management
B61: Com 19 | C61: =IF(AND('Check in'!B:B=B61,'Check in'!D:D="Good Condition"),"Usable","Not Usable") -> Not Usable | D61: 56601845 | E61: Phone | F61: Tumelo Makhetha | G61: 1 | H61: Sehonghong,Ha Lelingoana | I61: Samsung A02,Blue,6.5",32GB | J61: 351813381608810 | K61: WhatsApp Google Account | L61: Charger , Headsets | M61: Project Management
B62: Com 20 | C62: =IF(AND('Check in'!B:B=B62,'Check in'!D:D="Good Condition"),"Usable","Not Usable") -> Not Usable | D62: 56601812 | E62: Phone | F62: Tumelo Makhetha | G62: 1 | H62: Sehonghong,Ha Khomo ea Mollo | I62: Samsung A02,Blue,6.5",32GB | J62: 351813381571539 | K62: WhatsApp Google Account | L62: Charger , Headsets | M62: Project Management
B63: Com 21 | C63: =IF(AND('Check in'!B:B=B63,'Check in'!D:D="Good Condition"),"Usable","Not Usable") -> Not Usable | D63: 56601813 | E63: Phone | F63: Tumelo Makhetha | G63: 1 | H63: Sehonghong,Ha Mahlatsi | I63: Samsung A02,Blue,6.5",32GB | J63: 351813381594960 | K63: WhatsApp Google Account | L63: Charger , Headsets | M63: Project Management
B64: Com 22 | C64: =IF(AND('Check in'!B:B=B64,'Check in'!D:D="Good Condition"),"Usable","Not Usable") -> Not Usable | D64: 56601815 | E64: Phone | F64: Tumelo Makhetha | G64: 1 | H64: Lebakeng, Ha Tebalo | I64: Samsung A02,Blue,6.5",32GB | J64: 351813381635235 | K64: WhatsApp Google Account | L64: Charger , Headsets | M64: Project Management
... B76: Com 34 | C76: =IF(AND('Check in'!B:B=B76,'Check in'!D:D="Good Condition"),"Usable","Not Usable") -> Not Usable | D76: 56601788 | E76: Phone | F76: Tumelo Makhetha | G76: 1 | H76: Mokhotlong,Matsoaing,Ha Mokone | I76: Samsung A02,Blue,6.5",32GB | J76: 351813381599134 | K76: WhatsApp Google Account | L76: Charger , Headsets,screen protector,phone cover | M76: Project Management
B77: Com 35 | C77: =IF(AND('Check in'!B:B=B77,'Check in'!D:D="Good Condition"),"Usable","Not Usable") -> Not Usable | D77: 56601827 | E77: Phone | G77: 1 | H77: Reticulation | I77: Samsung A02,Blue,6.5",32GB | J77: 351813381603092 | K77: WhatsApp Google Account | L77: Charger , Headsets | M77: Reticulation
B78: Com 36 | C78: =IF(AND('Check in'!B:B=B78,'Check in'!D:D="Good Condition"),"Usable","Not Usable") -> Not Usable | D78: 56601789 | E78: Phone | F78: Tumelo Makhetha | G78: 1 | H78: Mokhotlong,Matsoaing,Khohloaneng | I78: Samsung A02,Blue,6.5",32GB | J78: 351813381607572 | K78: WhatsApp Google Account | L78: Charger , Headsets,screen protector,phone cover | M78: Project Management
B79: Com 37 | C79: Not Usable | D79: 56601802 | E79: Phone | G79: 1 | I79: Samsung A02,Blue,6.5",32GB | J79: 351813381595314 | K79: WhatsApp Google Account | L79: Charger , Headsets | M79: Project Management
B80: Com 38 | C80: =IF(AND('Check in'!B:B=B80,'Check in'!D:D="Good Condition"),"Usable","Not Usable") -> Not Usable | D80: 56601806 | E80: Phone | F80: Tumelo Makhetha | G80: 1 | H80: Mokhotlong,Matsoaing,Liphakoeng | I80: Samsung A02,Blue,6.5",32GB | J80: 351813381634055 | K80: WhatsApp Google Account | L80: Charger , Headsets,screen protector,phone cover | M80: Project Management
B81: Com 39 | C81: =IF(AND('Check in'!B:B=B81,'Check in'!D:D="Good Condition"),"Usable","Not Usable") -> Not Usable | D81: 56601800 | E81: Phone | F81: Tumelo Makhetha | G81: 1 | H81: Mokhotlong,Matsoaing,Liraoheleng | I81: Samsung A02,Blue,6.5",32GB | J81: 351813381608653 | K81: WhatsApp Google Account | L81: Charger , Headsets | M81: Project Management
B82: Com 40 | C82: Not Usable | D82: 56601810 | E82: Phone | G82: 1 | I82: Samsung A02,Blue,6.5",32GB | J82: 351813381599373 | K82: WhatsApp Google Account | L82: Charger , Headsets | M82: Project Management
B83: Com 41 | C83: =IF(AND('Check in'!B:B=B83,'Check in'!D:D="Good Condition"),"Usable","Not Usable") -> Not Usable | D83: 56601835 | E83: Phone | F83: Ralefaso | G83: 1 | H83: Fleet Department | I83: Samsung A02,Blue,6.5",32GB | J83: 351813381634683 | K83: WhatsApp Google Account | L83: Charger , Headsets,screen protector,phone cover | M83: Fleet
B84: Com 42 | C84: =IF(AND('Check in'!B:B=B84,'Check in'!D:D="Good Condition"),"Usable","Not Usable") -> Not Usable | D84: 56601805 | E84: Phone | F84: Tumelo Makhetha | G84: 1 | H84: Mokhotlong,Matsoaing,Masuaneng | I84: Samsung A02,Blue,6.5",32GB | J84: 351813381571638 | K84: WhatsApp Google Account | L84: Charger , Headsets | M84: Project Management
B85: Com 43 | C85: =IF(AND('Check in'!B:B=B85,'Check in'!D:D="Good Condition"),"Usable","Not Usable") -> Not Usable | D85: 56601808 | E85: Phone | F85: Tumelo Makhetha | G85: 1 | H85: Matsoaing,Sekoting | I85: Samsung A02,Blue,6.5",32GB | J85: 351813381603613 | K85: WhatsApp Google Account | L85: Charger , Headsets | M85: Project Management
B86: Com 44 | C86: =IF(AND('Check in'!B:B=B86,'Check in'!D:D="Good Condition"),"Usable","Not Usable") -> Not Usable | D86: 56601811 | E86: Phone | F86: Tumelo Makhetha | G86: 1 | H86: Matsoaing, Ha Setefane | I86: Samsung A02,Blue,6.5",32GB | J86: 351813381601377 | K86: WhatsApp Google Account | L86: Charger , Headsets | M86: Project Management
B87: Com 45 | C87: =IF(AND('Check in'!B:B=B87,'Check in'!D:D="Good Condition"),"Usable","Not Usable") -> Not Usable | D87: 56601807 | E87: Phone | F87: Tumelo Makhetha | G87: 1 | H87: Matsoaing, Tseko | I87: Samsung A02,Blue,6.5",32GB | J87: 351813381633461 | K87: WhatsApp Google Account | L87: Charger , Headsets | M87: Project Management
B88: COM46 | D88: 56002572 | E88: Phone | F88: P.M, MAT CUSTOMER SUPPORT | H88: HQ | I88: MOBICEL | K88: WhatsApp Google Account | M88: Project Management
B91: 006 | C91: =IF(AND('Check in'!B:B=B91,'Check in'!D:D="Good Condition"),"Usable","Not Usable") -> Not Usable | E91: Laptop | G91: 1 | J91: 5CG4442YLH
B92: 009 | C92: =IF(AND('Check in'!B:B=B92,'Check in'!D:D="Good Condition"),"Usable","Not Usable") -> Not Usable | E92: Laptop | G92: 1 | J92: GXJ89H2
B93: PMTEAM01 | C93: =IF(AND('Check in'!B:B=B93,'Check in'!D:D="Good Condition"),"Usable","Not Usable") -> Not Usable | E93: Laptop | F93: Tumelo Makhetha | G93: 1 | H93: PM Department | J93: M8N0CX03A078314 | L93: Mouse Mouse Pad Mounted Multi Plug | M93: Project Management
B94: PMTEAM02 | C94: =IF(AND('Check in'!B:B=B94,'Check in'!D:D="Good Condition"),"Usable","Not Usable") -> Not Usable | E94: Laptop | F94: Mongali Tlali | G94: 1 | H94: PM Department | J94: M8N0CX03A154319 | M94: Project Management
B95: 008 | C95: =IF(AND('Check in'!B:B=B95,'Check in'!D:D="Good Condition"),"Usable","Not Usable") -> Not Usable | E95: Laptop | G95: 1 | J95: 5CD7374R1V
B96: 0365 | C96: =IF(AND('Check in'!B:B=B96,'Check in'!D:D="Good Condition"),"Usable","Not Usable") -> Not Usable | E96: Laptop | G96: 1 | J96: L7N0GR02K51330A
B97: ADM01 | C97: =IF(AND('Check in'!B:B=B97,'Check in'!D:D="Good Condition"),"Usable","Not Usable") -> Not Usable | E97: Laptop | F97: Finance Department | G97: 1 | H97: Finance Department | J97: LBN0CX173888479 | M97: Finance
B98: EHS01 | C98: =IF(AND('Check in'!B:B=B98,'Check in'!D:D="Good Condition"),"Usable","Not Usable") -> Not Usable | E98: Laptop | F98: Maferete Moorosi | G98: 1 | H98: EHS Department | J98: GWTN156-1RG20LBM05267 | L98: Mouse Mouse Pad Extension Cord Universal Adapter | M98: EHS
B99: New02 | C99: =IF(AND('Check in'!B:B=B99,'Check in'!D:D="Good Condition"),"Usable","Not Usable") -> Not Usable | E99: Laptop | G99: 1 | J99: GWTN156-1RG20LBM06029
B100: EE001 | C100: =IF(AND('Check in'!B:B=B100,'Check in'!D:D="Good Condition"),"Usable","Not Usable") -> Not Usable | E100: Laptop | F100: Josias Molomo | G100: 1 | H100: EE Department | K100: Microsoft Office,Dropbox,Microsoft To Do set up by Motebang Lekhooana and Kamohelo Makaka Glasswire installed and set up by Tlhokomelo Kikine | L100: Charger Mouse USB Hub | M100: EE
B101: EE002 | C101: =IF(AND('Check in'!B:B=B101,'Check in'!D:D="Good Condition"),"Usable","Not Usable") -> Not Usable | E101: Laptop | F101: Thabo Monoto | G101: 1 | H101: EE Department | K101: Microsoft Office,Dropbox,Microsoft To Do set up by Motebang Lekhooana and Kamohelo Makaka Glasswire installed and set up by Tlhokomelo Kikine | L101: Charger Mouse | M101: EE
B102: EE003 | C102: =IF(AND('Check in'!B:B=B102,'Check in'!D:D="Good Condition"),"Usable","Not Usable") -> Not Usable | E102: Laptop | F102: Bokang Mothomotsoane | G102: 1 | H102: EE Department | I102: Hp Elitebook 840 G3 | K102: Microsoft Office,Dropbox,Microsoft To Do set up by Motebang Lekhooana and Kamohelo Makaka Glasswire installed and set up by Tlhokomelo Kikine | L102: Charger Mouse | M102: EE
B103: EE004 | C103: =IF(AND('Check in'!B:B=B103,'Check in'!D:D="Good Condition"),"Usable","Not Usable") -> Not Usable | E103: Laptop | F103: Tumisang Mathaba | G103: 1 | H103: EE Department | K103: Microsoft Office,Dropbox,Microsoft To Do set up by Motebang Lekhooana and Kamohelo Makaka Glasswire installed and set up by Tlhokomelo Kikine | L103: Charger Mouse | M103: EE
B104: EE005 | C104: =IF(AND('Check in'!B:B=B104,'Check in'!D:D="Good Condition"),"Usable","Not Usable") -> Not Usable | E104: Laptop | F104: Motebang Lekhooana | G104: 1 | H104: EE Department | K104: Microsoft Office,Dropbox,Microsoft To Do set up by Motebang Lekhooana and Kamohelo Makaka Glasswire installed and set up by Tlhokomelo Kikine | L104: Charger Mouse | M104: EE
B105: HR001 | C105: Usable | E105: Laptop | F105: Manneuoa Molefi | G105: 1 | H105: HR Department | I105: Hp Elitebook 840 G3 | J105: 5CG8105SVQ | L105: Charger Mounted Multi Plug | M105: HR
C106: =IF(AND('Check in'!B:B=B105,'Check in'!D:D="Good Condition"),"Usable","Not Usable") -> Not Usable | E106: Laptop | F106: Tlhokomelo Kikine | G106: 1 | H106: EE Department | I106: Hp Elitebook 840 G3 | K106: Microsoft Office,Dropbox,Microsoft To Do,Github,Android Studio Chrome,Glasswire installed and set up by Tlhokomelo Kikine | M106: EE
B107: RET 01 | C107: =IF(AND('Check in'!B:B=B107,'Check in'!D:D="Good Condition"),"Usable","Not Usable") -> Not Usable | E107: Laptop | F107: Reticulation | G107: 1 | H107: IT Locker | I107: Hp Elitebook 840 G3 | J107: 5CG625277T | K107: Microsoft Office,Dropbox,Microsoft To Do set up by Motebang Lekhooana and Kamohelo Makaka Glasswire installed and set up by Tlhokomelo Kikine | L107: Charger Mouse | M107: Reticulation
B108: RET 02 | C108: =IF(AND('Check in'!B:B=B108,'Check in'!D:D="Good Condition"),"Usable","Not Usable") -> Not Usable | E108: Laptop | F108: Reticulation | G108: 1 | H108: IT Locker | I108: Hp Elitebook 840 G3 | J108: 5CG6456QQBS | K108: Microsoft Office,Dropbox,Microsoft To Do set up by Motebang Lekhooana and Kamohelo Makaka Glasswire installed and set up by Tlhokomelo Kikine | L108: Charger Mouse | M108: Reticulation
B109: RET 03 | C109: =IF(AND('Check in'!B:B=B109,'Check in'!D:D="Good Condition"),"Usable","Not Usable") -> Not Usable | E109: Laptop | F109: Reticulation | G109: 1 | H109: IT Locker | I109: Hp Elitebook 840 G3 | J109: 5CG6456QD0 | K109: Microsoft Office,Dropbox,Microsoft To Do set up by Motebang Lekhooana and Kamohelo Makaka Glasswire installed and set up by Tlhokomelo Kikine | L109: Charger Mouse | M109: Reticulation
B110: RET 04 | C110: =IF(AND('Check in'!B:B=B110,'Check in'!D:D="Good Condition"),"Usable","Not Usable") -> Not Usable | E110: Laptop | F110: Reticulation | G110: 1 | H110: IT Locker | I110: Hp Elitebook 840 G3 | J110: 5CG61182257 | K110: Microsoft Office,Dropbox,Microsoft To Do set up by Motebang Lekhooana and Kamohelo Makaka Glasswire installed and set up by Tlhokomelo Kikine | L110: Charger Mouse | M110: Reticulation
B111: RET 05 | C111: =IF(AND('Check in'!B:B=B111,'Check in'!D:D="Good Condition"),"Usable","Not Usable") -> Not Usable | E111: Laptop | F111: Reticulation | G111: 1 | H111: IT Locker | I111: Hp Elitebook 840 G3 | J111: 5CG7061S2N | K111: Microsoft Office,Dropbox,Microsoft To Do set up by Motebang Lekhooana and Kamohelo Makaka Glasswire installed and set up by Tlhokomelo Kikine | L111: Charger Mouse | M111: Reticulation
B112: RET 06 | C112: =IF(AND('Check in'!B:B=B112,'Check in'!D:D="Good Condition"),"Usable","Not Usable") -> Not Usable | E112: Laptop | F112: Reticulation | G112: 1 | H112: IT Locker | I112: Hp Elitebook 840 G3 | J112: 5CG63809T1 | K112: Microsoft Office,Dropbox,Microsoft To Do set up by Motebang Lekhooana and Kamohelo Makaka Glasswire installed and set up by Tlhokomelo Kikine | L112: Charger Mouse | M112: Reticulation
B113: RET 07 | C113: =IF(AND('Check in'!B:B=B113,'Check in'!D:D="Good Condition"),"Usable","Not Usable") -> Not Usable | E113: Laptop | F113: Reticulation | G113: 1 | H113: IT Locker | I113: Hp Elitebook 840 G3 | J113: 5CG64150NP | K113: Microsoft Office,Dropbox,Microsoft To Do set up by Motebang Lekhooana and Kamohelo Makaka Glasswire installed and set up by Tlhokomelo Kikine | L113: Charger Mouse | M113: Reticulation
B114: RET 08 | C114: =IF(AND('Check in'!B:B=B114,'Check in'!D:D="Good Condition"),"Usable","Not Usable") -> Not Usable | E114: Laptop | F114: Reticulation | G114: 1 | H114: IT Locker | I114: Hp Elitebook 840 G3 | J114: 5CG6456Q62 | K114: Microsoft Office,Dropbox,Microsoft To Do set up by Motebang Lekhooana and Kamohelo Makaka Glasswire installed and set up by Tlhokomelo Kikine | L114: Charger Mouse | M114: Reticulation
...

Sheet Untaggable
A1: Chargers | B1: Quantity | D1: Cables and Adapters | E1: Quantity | G1: Tools | H1: Quantity | J1: Equipment | K1: Quantity
A2: HP | B2: 6 | D2: Kenable Power Cable | E2: 22 | G2: cctv cameras | H2: 13 | J2: Label Maker | K2: 2
A3: Dell | B3: 5 | D3: 3-pin Power Cable | E3: 5 | G3: NVR | H3: 1 | J3: Tablets Covers model 7 | K3: 27
A4: TV | B4: 1 | D4: Ethernet | E4: 7 | G4: Flat Screw Driver | H4: 2 | J4: Tablets Screen Protectors | K4: 10
A5: Blackberry | B5: 1 | D5: HDMI | E5: 5 | G5: Blades Set | H5: 1 | J5: Phone covers | K5: 47
A6: Asus | B6: 1 | D6: Vga | E6: 7 | G6: Side Cutter | H6: 2 | J6: Phone Screen Protectors | K6: 47
D7: Display to HDMI | E7: 8 | G7: 11.5" Drill Bit Set | H7: 1 | J7: Flash Drive | K7: 1
D8: VGA to HDMI | E8: 5 | G8: Wire Strippers | H8: 3 | J8: Power Banks | K8: 1
D9: Ethernet Adapter | E9: 1 | G9: Stripping Gun | H9: 2
D10: Extension Cord | E10: 1 | G10: Pliers | H10: 3
D11: Universal Adapters | E11: 10 | G11: Crimping tool | H11: 1
D12: 2 Pin Plug Adapter | E12: 3 | G12: Vice Grip | H12: 1
D13: Aux Cable | E13: 1 | G13: Nail Stripper/Puller | H13: 1
D14: Male USB-USB | E14: 3 | G14: Soldering Iron Sucker | H14: 1
D15: Female USB-USB | E15: 2 | G15: Load Balance/Batrpas | H15: 1
D16: USB B 2.0 | E16: 7 | G16: Measuring Tape | H16: 1
D17: Stereo Adapters | E17: 2 | G17: Chisel | H17: 1
D18: Victron Energy Power Cables | E18: 1 | G18: Solar Panels | H18: 4
D19: Victron Energy Direct-USB | E19: 1 | G19: G3 Fatbox Modem | H19: 1
D20: Earphone-mic (K-type) | E20: 6 | G20: POE Switch | H20: 1
... D27: PC Tire Cable | E27: 1 | G27: Thermal Sensors | H27: 2
D28: Wifi Adapter | G28: DI-158U | H28: 1
G29: Expansion Module | H29: 1
G30: SDM120 | H30: 1
G31: SDM530 | H31: 1
G32: LED display | H32: 1
G33: Transducer | H33: 1
G34: Speedometer | H34: 1
G35: Programmable K-Factor Scaler | H35: 1
G36: Modified Sinewave Inverter | H36: 1
G37: Tachometer | H37: 1
G38: DC-DC converter | H38: 2
G39: Crocodile clips | H39: 1

Sheet Detailed Approval Records Forme
A1: Timestamp | B1: Response Id | C1: Request # | D1: Revision # | E1: Overall Status | F1: Requestor | G1: Edit Response Url | H1: Total Recipients | I1: Participant Ids | J1: Recipient 1 | K1: Recipient 1 Status | L1: Recipient 1 Issue Date | M1: Recipient 1 Response Date | N1: Recipient 1 Comment | O1: Recipient 1 Settings | P1: Recipient 2 | Q1: Recipient 2 Status | R1: Recipient 2 Issue Date | S1: Recipient 2 Response Date | T1: Recipient 2 Comment | U1: Recipient 2 Settings | V1: Recipient 3 | W1: Recipient 3 Status | X1: Recipient 3 Issue Date | Y1: Recipient 3 Response Date | Z1: Recipient 3 Comment | AA1: Recipient 3 Settings | AB1: Recipient 4 | AC1: Recipient 4 Status | AD1: Recipient 4 Issue Date | AE1: Recipient 4 Response Date | AF1: Recipient 4 Comment | AG1: Recipient 4 Settings | AH1: Recipient 5 | AI1: Recipient 5 Status | AJ1: Recipient 5 Issue Date | AK1: Recipient 5 Response Date | AL1: Recipient 5 Comment | AM1: Recipient 5 Settings | AN1: Recipient 6 | AO1: Recipient 6 Status | AP1: Recipient 6 Issue Date | AQ1: Recipient 6 Response Date | AR1: Recipient 6 Comment | AS1: Recipient 6 Settings | AT1: Recipient 7 | AU1: Recipient 7 Status | AV1: Recipient 7 Issue Date | AW1: Recipient 7 Response Date | AX1: Recipient 7 Comment | AY1: Recipient 7 Settings | AZ1: Recipient 8 | BA1: Recipient 8 Status | BB1: Recipient 8 Issue Date | BC1: Recipient 8 Response Date | BD1: Recipient 8 Comment | BE1: Recipient 8 Settings | BF1: Recipient 9 | BG1: Recipient 9 Status | BH1: Recipient 9 Issue Date | BI1: Recipient 9 Response Date | BJ1: Recipient 9 Comment | BK1: Recipient 9 Settings | BL1: Recipient 10 | BM1: Recipient 10 Status | BN1: Recipient 10 Issue Date | BO1: Recipient 10 Response Date | BP1: Recipient 10 Comment | BQ1: Recipient 10 Settings
A2: 44775.382 | B2: 2_ABaOnue4Eu6_Ad35HQhEU7MQSDxx17F95eiNQfCTzbj_F8Xk82lcrT_WxsY8_naD6h68x0g | C2: 1 | D2: 0 | E2: Complete | G2: https://docs.google.com/forms/d/e/1FAIpQLSfozIV5FQqcQNjQaUk40v9z-N0PHEZT8xM98Ndh72nkn88rVw/viewform?edit2=2_ABaOnue4Eu6_Ad35HQhEU7MQSDxx17F95eiNQfCTzbj_F8Xk82lcrT_WxsY8_naD6h68x0g | H2: 1 | I2: {"Recipients":[{"it-support@1pwrafrica.com":"9e05d7"}]} | J2: it-support@1pwrafrica.com | K2: Approved | L2: 44775.382 | M2: 44775.383 | N2: Cool | O2: {"Order":1,"Role":"Needs to Approve"}
A3: 44775.388 | B3: 2_ABaOnudjurLp6LV8QSahFYxPW0qh8ygNrZhaYXI-VylRQ5sgRXEOmiHoqS6LhnSUJF_A7Mc | C3: 2 | D3: 0 | E3: Complete | G3: https://docs.google.com/forms/d/e/1FAIpQLSfozIV5FQqcQNjQaUk40v9z-N0PHEZT8xM98Ndh72nkn88rVw/viewform?edit2=2_ABaOnudjurLp6LV8QSahFYxPW0qh8ygNrZhaYXI-VylRQ5sgRXEOmiHoqS6LhnSUJF_A7Mc | H3: 1 | I3: {"Recipients":[{"it-support@1pwrafrica.com":"563d42"}]} | J3: it-support@1pwrafrica.com | K3: Approved | L3: 44775.388 | M3: 44775.388 | N3: Will bring it to you sir, Regards Motebang | O3: {"Order":1,"Role":"Needs to Approve"}
A4: 44775.442 | B4: 2_ABaOnud-xDqTyBXea4vq8CNk3uI-O3hu3OSTGrPINCeMtBidsMMgHkutA8HFzIcq2Nxq4R0 | C4: 3 | D4: 0 | E4: Complete | G4: https://docs.google.com/forms/d/e/1FAIpQLSfozIV5FQqcQNjQaUk40v9z-N0PHEZT8xM98Ndh72nkn88rVw/viewform?edit2=2_ABaOnud-xDqTyBXea4vq8CNk3uI-O3hu3OSTGrPINCeMtBidsMMgHkutA8HFzIcq2Nxq4R0 | H4: 1 | I4: {"Recipients":[{"it-support@1pwrafrica.com":"5b1744"}]} | J4: it-support@1pwrafrica.com | K4: Approved | L4: 44775.442 | M4: 44775.473 | N4: Noted ntate, But the problem for now is delay because we will have to ask Matt to come with it from the US. Regards, Motebang | O4: {"Order":1,"Role":"Needs to Approve"}
A5: 44775.479 | B5: 2_ABaOnue1kh6j4-3aIPvR8566wUur47LHHE5vyUmInFPBGyMbbD6tWa9FKc7hXC1FUpeLMJQ | C5: 4 | D5: 0 | E5: Complete | G5: https://docs.google.com/forms/d/e/1FAIpQLSfozIV5FQqcQNjQaUk40v9z-N0PHEZT8xM98Ndh72nkn88rVw/viewform?edit2=2_ABaOnue1kh6j4-3aIPvR8566wUur47LHHE5vyUmInFPBGyMbbD6tWa9FKc7hXC1FUpeLMJQ | H5: 1 | I5: {"Recipients":[{"it-support@1pwrafrica.com":"30deeb"}]} | J5: it-support@1pwrafrica.com | K5: Approved | L5: 44775.479 | M5: 44775.48 | N5: test | O5: {"Order":1,"Role":"Needs to Approve"}
A6: 44775.49 | B6: 2_ABaOnudEJTUEVNc2CSaWnLue_fW9mhxr6KdaaPeBFRitTJOrR4RIsknyxbRjEXZuaxok4kU | C6: 5 | D6: 0 | E6: Complete | G6: https://docs.google.com/forms/d/e/1FAIpQLSfozIV5FQqcQNjQaUk40v9z-N0PHEZT8xM98Ndh72nkn88rVw/viewform?edit2=2_ABaOnudEJTUEVNc2CSaWnLue_fW9mhxr6KdaaPeBFRitTJOrR4RIsknyxbRjEXZuaxok4kU | H6: 1 | I6: {"Recipients":[{"it-support@1pwrafrica.com":"9957f6"}]} | J6: it-support@1pwrafrica.com | K6: Approved | L6: 44775.49 | M6: 44775.492 | N6: Noted, will discuss this with my colleagues for what need to be done ASAP, Regards, Motebang | O6: {"Order":1,"Role":"Needs to Approve"}
A7: 44775.616 | B7: 2_ABaOnuca4xu6hq5XvIc13-ntaT6bMlDoY4n_WcD_w4XPC_MVgzUsj1wUop-IjKrK3pKJxDk | C7: 6 | D7: 0 | E7: In progress | G7: https://docs.google.com/forms/d/e/1FAIpQLSfozIV5FQqcQNjQaUk40v9z-N0PHEZT8xM98Ndh72nkn88rVw/viewform?edit2=2_ABaOnuca4xu6hq5XvIc13-ntaT6bMlDoY4n_WcD_w4XPC_MVgzUsj1wUop-IjKrK3pKJxDk | H7: 1 | I7: {"Recipients":[{"it-support@1pwrafrica.com":"26d992"}]} | J7: it-support@1pwrafrica.com | K7: Current | L7: 44775.616 | O7: {"Order":1,"Role":"Needs to Approve"}
A8: 44775.703 | B8: 2_ABaOnudHB8wKML1X73pfGpgETyKbERSBy5E_SSv_y90-USBEPJ2DN4cjujjLAhG9WW52j_k | C8: 7 | D8: 0 | E8: Complete | G8: https://docs.google.com/forms/d/e/1FAIpQLSfozIV5FQqcQNjQaUk40v9z-N0PHEZT8xM98Ndh72nkn88rVw/viewform?edit2=2_ABaOnudHB8wKML1X73pfGpgETyKbERSBy5E_SSv_y90-USBEPJ2DN4cjujjLAhG9WW52j_k | H8: 1 | I8: {"Recipients":[{"it-support@1pwrafrica.com":"2df96b"}]} | J8: it-support@1pwrafrica.com | K8: Approved | L8: 44775.703 | M8: 44775.706 | O8: {"Order":1,"Role":"Needs to Approve"}
A9: 44776.49 | B9: 2_ABaOnucbmw1RilpVWedpHjBFAUNYMOXo2q_OnOhVbdxYZSpyb1afIMDLrxKBY37Zvjc5Xic | C9: 8 | D9: 0 | E9: Complete | G9: https://docs.google.com/forms/d/e/1FAIpQLSfozIV5FQqcQNjQaUk40v9z-N0PHEZT8xM98Ndh72nkn88rVw/viewform?edit2=2_ABaOnucbmw1RilpVWedpHjBFAUNYMOXo2q_OnOhVbdxYZSpyb1afIMDLrxKBY37Zvjc5Xic | H9: 1 | I9: {"Recipients":[{"it-support@1pwrafrica.com":"99c6aa"}]} | J9: it-support@1pwrafrica.com | K9: Approved | L9: 44776.49 | M9: 44776.51 | N9: I'm on it, Will be resolved. Regards, Motebang | O9: {"Order":1,"Role":"Needs to Approve"}
A10: 44776.597 | B10: 2_ABaOnudJzcqFjAG1XvUNWcKlFZeawfyXRSiLHHmz0QhFN40yJkJXoIMRY_6NyWx0uxXGU1A | C10: 9 | D10: 0 | E10: Complete | G10: https://docs.google.com/forms/d/e/1FAIpQLSfozIV5FQqcQNjQaUk40v9z-N0PHEZT8xM98Ndh72nkn88rVw/viewform?edit2=2_ABaOnudJzcqFjAG1XvUNWcKlFZeawfyXRSiLHHmz0QhFN40yJkJXoIMRY_6NyWx0uxXGU1A | H10: 1 | I10: {"Recipients":[{"it-support@1pwrafrica.com":"f82741"}]} | J10: it-support@1pwrafrica.com | K10: Approved | L10: 44776.597 | M10: 44776.671 | N10: We will let people responsible for such maintanances resolve that. Tumisang is absent and we do not have a spare multiplug. Regards, Motebang | O10: {"Order":1,"Role":"Needs to Approve"}
A11: 44776.668 | B11: 2_ABaOnufqRSi40ZhvlzspC-Vk8CDJ5RbjEG5ck5Zohcb1QQECiu38SMaTlsAH6VUM4_tRjYY | C11: 10 | D11: 0 | E11: Complete | G11: https://docs.google.com/forms/d/e/1FAIpQLSfozIV5FQqcQNjQaUk40v9z-N0PHEZT8xM98Ndh72nkn88rVw/viewform?edit2=2_ABaOnufqRSi40ZhvlzspC-Vk8CDJ5RbjEG5ck5Zohcb1QQECiu38SMaTlsAH6VUM4_tRjYY | H11: 1 | I11: {"Recipients":[{"it-support@1pwrafrica.com":"411e70"}]} | J11: it-support@1pwrafrica.com | K11: Approved | L11: 44776.668 | M11: 44776.669 | N11: Yes, it has to have it. I will come around to help regarding that. Regards, Motebang | O11: {"Order":1,"Role":"Needs to Approve"}
A12: 44777.413 | B12: 2_ABaOnuczbTnIl-__iv7abFm9k7FdjOi1zpdcVefX2FPV5FjjMl_JdFO5ZLMPwAwYkjdtXWw | C12: 11 | D12: 0 | E12: In progress | G12: https://docs.google.com/forms/d/e/1FAIpQLSfozIV5FQqcQNjQaUk40v9z-N0PHEZT8xM98Ndh72nkn88rVw/viewform?edit2=2_ABaOnuczbTnIl-__iv7abFm9k7FdjOi1zpdcVefX2FPV5FjjMl_JdFO5ZLMPwAwYkjdtXWw | H12: 1 | I12: {"Recipients":[{"it-support@1pwrafrica.com":"54aff5"}]} | J12: it-support@1pwrafrica.com | K12: Current | L12: 44777.413 | O12: {"Order":1,"Role":"Needs to Approve"}
A13: 44777.422 | B13: 2_ABaOnueqMXi5tSqNk49VVxy61YJ-VKr5aAxrZUJjOFqb_g_46CdV0T-WZbtEnCZDtgzeO8U | C13: 12 | D13: 0 | E13: Complete | G13: https://docs.google.com/forms/d/e/1FAIpQLSfozIV5FQqcQNjQaUk40v9z-N0PHEZT8xM98Ndh72nkn88rVw/viewform?edit2=2_ABaOnueqMXi5tSqNk49VVxy61YJ-VKr5aAxrZUJjOFqb_g_46CdV0T-WZbtEnCZDtgzeO8U | H13: 1 | I13: {"Recipients":[{"it-support@1pwrafrica.com":"5a3400"}]} | J13: it-support@1pwrafrica.com | K13: Approved | L13: 44777.422 | M13: 44777.431 | O13: {"Order":1,"Role":"Needs to Approve"}
A14: 44777.49 | B14: 2_ABaOnufC8y503gzhce0cm96FFTNhQ4B3gQSHmVWuB7GGKbEmBHxhecskjENFRVXFCrcFAg4 | C14: 13 | D14: 0 | E14: Complete | G14: https://docs.google.com/forms/d/e/1FAIpQLSfozIV5FQqcQNjQaUk40v9z-N0PHEZT8xM98Ndh72nkn88rVw/viewform?edit2=2_ABaOnufC8y503gzhce0cm96FFTNhQ4B3gQSHmVWuB7GGKbEmBHxhecskjENFRVXFCrcFAg4 | H14: 1 | I14: {"Recipients":[{"it-support@1pwrafrica.com":"891ef4"}]} | J14: it-support@1pwrafrica.com | K14: Approved | L14: 44777.49 | M14: 44777.708 | N14: Ntate Jonase, your request is noted but we currently do not have available laptops in the office. We will allocate you one when they are here. Regards, Motebang | O14: {"Order":1,"Role":"Needs to Approve"}
A15: 44781.49 | B15: 2_ABaOnud6vK1U6ocPiYV0eHtp-aD1Jy8R1fHifm-izkmhVVHkRglaSD2-vtCjPj9xbBq4Rdg | C15: 14 | D15: 0 | E15: In progress | G15: https://docs.google.com/forms/d/e/1FAIpQLSfozIV5FQqcQNjQaUk40v9z-N0PHEZT8xM98Ndh72nkn88rVw/viewform?edit2=2_ABaOnud6vK1U6ocPiYV0eHtp-aD1Jy8R1fHifm-izkmhVVHkRglaSD2-vtCjPj9xbBq4Rdg | H15: 1 | I15: {"Recipients":[{"it-support@1pwrafrica.com":"6aa5f5"}]} | J15: it-support@1pwrafrica.com | K15: Current | L15: 44781.49 | O15: {"Order":1,"Role":"Needs to Approve"}
A16: 44781.682 | B16: 2_ABaOnudOZMLJJFL-J0hJ9fD9xL9BhW5VRcHLMgz-KPk7dMliRZ13Z401hRPAh1DGRvKDhoo | C16: 15 | D16: 0 | E16: In progress | G16: https://docs.google.com/forms/d/e/1FAIpQLSfozIV5FQqcQNjQaUk40v9z-N0PHEZT8xM98Ndh72nkn88rVw/viewform?edit2=2_ABaOnudOZMLJJFL-J0hJ9fD9xL9BhW5VRcHLMgz-KPk7dMliRZ13Z401hRPAh1DGRvKDhoo | H16: 1 | I16: {"Recipients":[{"it-support@1pwrafrica.com":"cae945"}]} | J16: it-support@1pwrafrica.com | K16: Current | L16: 44781.682 | O16: {"Order":1,"Role":"Needs to Approve"}
A17: 44783.381 | B17: 2_ABaOnudw6QRmmFAKoeX4tBp05NDTXUo0du2C3cvSQayHH5_r8yCdObh-XUsjGfSF_2RGESY | C17: 16 | D17: 0 | E17: Complete | G17: https://docs.google.com/forms/d/e/1FAIpQLSfozIV5FQqcQNjQaUk40v9z-N0PHEZT8xM98Ndh72nkn88rVw/viewform?edit2=2_ABaOnudw6QRmmFAKoeX4tBp05NDTXUo0du2C3cvSQayHH5_r8yCdObh-XUsjGfSF_2RGESY | H17: 1 | I17: {"Recipients":[{"it-support@1pwrafrica.com":"7fe1b8"}]} | J17: it-support@1pwrafrica.com | K17: Approved | L17: 44783.381 | M17: 44783.381 | O17: {"Order":1,"Role":"Needs to Approve"}
A18: 44783.392 | B18: 2_ABaOnucnGo7KBHFENF-jgHWkiRhzKeeOVndIybRvisjxoiZ745JMg0xP3tbB7GbpiG-hu3A | C18: 17 | D18: 0 | E18: Complete | G18: https://docs.google.com/forms/d/e/1FAIpQLSfozIV5FQqcQNjQaUk40v9z-N0PHEZT8xM98Ndh72nkn88rVw/viewform?edit2=2_ABaOnucnGo7KBHFENF-jgHWkiRhzKeeOVndIybRvisjxoiZ745JMg0xP3tbB7GbpiG-hu3A | H18: 1 | I18: {"Recipients":[{"it-support@1pwrafrica.com":"2cbf20"}]} | J18: it-support@1pwrafrica.com | K18: Approved | L18: 44783.393 | M18: 44783.395 | O18: {"Order":1,"Role":"Needs to Approve"}
A19: 44784.647 | B19: 2_ABaOnufTJdP4DiN6eWLgFMUgRIvWv6lNkwbiCq5_81-Sg4b5zkCtXKMw0CNQ2zZSap1BgrM | C19: 18 | D19: 0 | E19: In progress | G19: https://docs.google.com/forms/d/e/1FAIpQLSfozIV5FQqcQNjQaUk40v9z-N0PHEZT8xM98Ndh72nkn88rVw/viewform?edit2=2_ABaOnufTJdP4DiN6eWLgFMUgRIvWv6lNkwbiCq5_81-Sg4b5zkCtXKMw0CNQ2zZSap1BgrM | H19: 1 | I19: {"Recipients":[{"it-support@1pwrafrica.com":"1aa233"}]} | J19: it-support@1pwrafrica.com | K19: Current | L19: 44784.647 | O19: {"Order":1,"Role":"Needs to Approve"}
A20: 44785.339 | B20: 2_ABaOnuecrtdfp4dLK5zxwKJufZRTJ8GiN4GjM-Yuwya_JnJ7NlIaA4o3lH0dljQXfYsiLrA | C20: 19 | D20: 0 | E20: Complete | G20: https://docs.google.com/forms/d/e/1FAIpQLSfozIV5FQqcQNjQaUk40v9z-N0PHEZT8xM98Ndh72nkn88rVw/viewform?edit2=2_ABaOnuecrtdfp4dLK5zxwKJufZRTJ8GiN4GjM-Yuwya_JnJ7NlIaA4o3lH0dljQXfYsiLrA | H20: 1 | I20: {"Recipients":[{"it-support@1pwrafrica.com":"d7e968"}]} | J20: it-support@1pwrafrica.com | K20: Approved | L20: 44785.339 | M20: 44785.473 | O20: {"Order":1,"Role":"Needs to Approve"}
A21: 44788.661 | B21: 2_ABaOnufWELP0RrG4QN1k4zZsFcckF7oztfwh4edD8w9itsYPC7T3xUH1Ysr6w41F4abFC-8 | C21: 20 | D21: 0 | E21: Complete | G21: https://docs.google.com/forms/d/e/1FAIpQLSfozIV5FQqcQNjQaUk40v9z-N0PHEZT8xM98Ndh72nkn88rVw/viewform?edit2=2_ABaOnufWELP0RrG4QN1k4zZsFcckF7oztfwh4edD8w9itsYPC7T3xUH1Ysr6w41F4abFC-8 | H21: 1 | I21: {"Recipients":[{"it-support@1pwrafrica.com":"124408"}]} | J21: it-support@1pwrafrica.com | K21: Approved | L21: 44788.661 | M21: 44788.673 | O21: {"Order":1,"Role":"Needs to Approve"}

Sheet Detailed Approval Report
A1: # | B1: Unique Request # | C1: Timestamp | D1: Respondent | E1: Final Status | F1: Recipient 1 | J1: Recipient 2 | N1: Recipient 3 | R1: Recipient 4 | V1: Recipient 5 | Z1: Recipient 6 | AD1: Recipient 7 | AH1: Recipient 8 | AL1: Recipient 9 | AP1: Recipient 10
F2: Recipient 1 Email | G2: Recipient 1 Status | H2: Recipient 1 Comment | I2: Recipient 1 Response Date | J2: Recipient 2 Email | K2: Recipient 2 Status | L2: Recipient 2 Comment | M2: Recipient 2 Response Date | N2: Recipient 3 Email | O2: Recipient 3 Status | P2: Recipient 3 Comment | Q2: Recipient 3 Response Date | R2: Recipient 4 Email | S2: Recipient 4 Status | T2: Recipient 4 Comment | U2: Recipient 4 Response Date | V2: Recipient 5 Email | W2: Recipient 5 Status | X2: Recipient 5 Comment | Y2: Recipient 5 Response Date | Z2: Recipient 6 Email | AA2: Recipient 6 Status | AB2: Recipient 6 Comment | AC2: Recipient 6 Response Date | AD2: Recipient 7 Email | AE2: Recipient 7 Status | AF2: Recipient 7 Comment | AG2: Recipient 7 Response Date | AH2: Recipient 8 Email | AI2: Recipient 8 Status | AJ2: Recipient 8 Comment | AK2: Recipient 8 Response Date | AL2: Recipient 9 Email | AM2: Recipient 9 Status | AN2: Recipient 9 Comment | AO2: Recipient 9 Response Date | AP2: Recipient 10 Email | AQ2: Recipient 10 Status | AR2: Recipient 10 Comment | AS2: Recipient 10 Response Date
A3: 29 | C3: 05/31/2022 09:12:44 | D3: cadkikine@gmail.com | E3: Rejected | F3: it-support@1pwrafrica.com | G3: Rejected | I3: 05/31/2022 09:16:32
A4: 30 | C4: 05/31/2022 09:21:09 | D4: cadkikine@gmail.com | E4: Approved | F4: it-support@1pwrafrica.com | G4: Approved | H4: . | I4: 05/31/2022 09:23:00
A5: 31 | C5: 05/31/2022 09:24:35 | D5: cadkikine@gmail.com | E5: In Progress | F5: it-support@1pwrafrica.com
A6: 32 | C6: 05/31/2022 09:25:40 | D6: cadkikine@gmail.com | E6: In Progress | F6: it-support@1pwrafrica.com
A7: 33 | C7: 44718.318 | D7: makhoalinyane@1pwrafrica.com | E7: Approved | F7: it-support@1pwrafrica.com | G7: Approved | I7: 44718.319
A8: 34 | C8: 44718.323 | D8: mosehle@1pwrafrica.com | E8: In Progress | F8: it-support@1pwrafrica.com
A9: 35 | C9: 44718.326 | D9: kubutu@1pwrafrica.com | E9: In Progress | F9: it-support@1pwrafrica.com
A10: 36 | C10: 44718.333 | D10: ernestmoloantoateb@gmail.com | E10: In Progress | F10: it-support@1pwrafrica.com
A11: 37 | C11: 44718.375 | D11: monoane@1pwrafrica.com | E11: In Progress | F11: it-support@1pwrafrica.com
A12: 38 | C12: 44718.605 | D12: leloko@1pwrafrica.com | E12: In Progress | F12: it-support@1pwrafrica.com
A13: 39 | C13: 44718.613 | D13: makhoalinyane@1pwrafrica.com | E13: In Progress | F13: it-support@1pwrafrica.com
A14: 40 | C14: 44718.627 | D14: mosehle@1pwrafrica.com | E14: In Progress | F14: it-support@1pwrafrica.com
A15: 41 | C15: 44748.312 | D15: makoetje@1pwrafrica.com | E15: Approved | F15: it-support@1pwrafrica.com | G15: Approved | I15: 44748.314
A16: 42 | C16: 44748.401 | D16: jopi@1pwrafrica.com | E16: Approved | F16: it-support@1pwrafrica.com | G16: Approved | I16: 44748.401
A17: 43 | C17: 44748.442 | D17: moeketse@1pwrafrica.com | E17: Approved | F17: it-support@1pwrafrica.com | G17: Approved | H17: It is being attended to. | I17: 44748.448
A18: 44 | C18: 44748.529 | D18: jonase@1pwrafrica.com | E18: Approved | F18: it-support@1pwrafrica.com | G18: Approved | I18: 44779.285
A19: 45 | C19: 44779.308 | D19: david@1pwrafrica.com | E19: In Progress | F19: it-support@1pwrafrica.com
A20: 46 | C20: 44779.315 | D20: lichabajameswest@gmail.com | E20: Approved | F20: it-support@1pwrafrica.com | G20: Approved | H20: We are still waiting fopr the laptops that Matt told us he will come with so once they are here we will give you one. | I20: 44779.333
A21: 47 | C21: 44779.618 | D21: mothomotsoanabk@gmail.com | E21: Approved | F21: it-support@1pwrafrica.com | G21: Approved | I21: 44779.127
A22: 48 | C22: 44810.392 | D22: mlanjenijoshua@gmail.com | E22: In Progress | F22: it-support@1pwrafrica.com
A23: 49 | C23: 44840.328 | D23: abele@1pwrafrica.com | E23: Approved | F23: it-support@1pwrafrica.com | G23: Approved | I23: 44840.329
A24: 50 | C24: 44840.5 | D24: phoka@1pwrafrica.com | E24: Approved | F24: it-support@1pwrafrica.com | G24: Approved | I24: 06/13/2022 10:51:02
A25: 51 | C25: 06/13/2022 06:12:21 | D25: thakhisinthabiseng@gmail.com | E25: Approved | F25: it-support@1pwrafrica.com | G25: Approved | I25: 06/13/2022 07:08:18
A26: 52 | C26: 06/13/2022 09:43:16 | D26: maferete@1pwrafrica.com | E26: Rejected | F26: it-support@1pwrafrica.com | G26: Rejected | H26: The parts are currently unavailable. Please make an equipment request. | I26: 06/13/2022 10:05:45
A27: 53 | C27: 06/13/2022 10:08:35 | D27: lichabajameswest@gmail.com | E27: In Progress | F27: it-support@1pwrafrica.com
A28: 54 | C28: 06/13/2022 10:37:04 | D28: morema@1pwrafrica.com | E28: In Progress | F28: it-support@1pwrafrica.com
A29: 55 | C29: 06/13/2022 10:40:54 | D29: morema@1pwrafrica.com | E29: Approved | F29: it-support@1pwrafrica.com | G29: Approved | H29: Noted. We'll have to make a request for it's replacement. | I29: 06/13/2022 10:48:32
A30: 56 | C30: 06/13/2022 10:50:01 | D30: phoka@1pwrafrica.com | E30: In Progress | F30: it-support@1pwrafrica.com
A31: 57 | C31: 06/13/2022 10:55:52 | D31: phoka@1pwrafrica.com | E31: In Progress | F31: it-support@1pwrafrica.com
A32: 58 | C32: 06/13/2022 11:22:09 | D32: cadkikine@gmail.com | E32: In Progress | F32: it-support@1pwrafrica.com
A33: 59 | C33: 06/13/2022 15:10:53 | D33: makoetje@1pwrafrica.com | E33: In Progress | F33: it-support@1pwrafrica.com
A34: 60 | C34: 06/14/2022 07:34:14 | D34: morema@1pwrafrica.com | E34: In Progress | F34: it-support@1pwrafrica.com
A35: 61 | C35: 06/14/2022 07:41:03 | D35: Ramatla@1pwrafrica.com | E35: In Progress | F35: it-support@1pwrafrica.com
A36: 62 | C36: 06/14/2022 09:44:56 | D36: molefe@1pwrafrica.com | E36: Approved | F36: it-support@1pwrafrica.com | G36: Approved | H36: Please communicate with Mme Molefi | I36: 06/14/2022 02:42:18
A37: 63 | C37: 06/15/2022 13:35:52 | D37: lichabajameswest@gmail.com | E37: Approved | F37: it-support@1pwrafrica.com | G37: Approved | I37: 06/15/2022 01:37:26
A38: 64 | C38: 06/15/2022 13:41:50 | D38: tkemathaba@gmail.com | E38: Rejected | F38: it-support@1pwrafrica.com | G38: Rejected | H38: You don't just decide this. Talk to your lead, IT does not deal with company finances also. | I38: 06/15/2022 01:46:25
A39: 65 | C39: 06/17/2022 07:25:09 | D39: monoane@1pwrafrica.com | E39: Approved | F39: it-support@1pwrafrica.com | G39: Approved | I39: 06/17/2022 07:43:30
A40: 66 | C40: 06/17/2022 07:59:50 | D40: monoane@1pwrafrica.com | E40: Approved | F40: it-support@1pwrafrica.com | G40: Approved | I40: 06/17/2022 09:08:57
A41: 67 | C41: 06/17/2022 08:44:57 | D41: mothomotsoanabk@gmail.com | E41: Approved | F41: it-support@1pwrafrica.com | G41: Approved | H41: Tou will have access to Cappped Wi-Fi for today. | I41: 06/17/2022 09:07:59
A42: 68 | C42: 06/17/2022 09:07:10 | D42: phoka@1pwrafrica.com | E42: Approved | F42: it-support@1pwrafrica.com | G42: Approved | H42: You can come get a mouse pad. | I42: 06/17/2022 09:09:36
A43: 69 | C43: 06/20/2022 09:58:05 | D43: mothomotsoanabk@gmail.com | E43: Approved | F43: it-support@1pwrafrica.com | G43: Approved | I43: 06/20/2022 01:18:19
A44: 70 | C44: 06/21/2022 13:25:39 | D44: david@1pwrafrica.com | E44: Approved | F44: it-support@1pwrafrica.com | G44: Approved | H44: Noted. We will do that. | I44: 06/21/2022 08:00:03
A45: 71 | C45: 06/22/2022 14:23:34 | D45: lichabajameswest@gmail.com | E45: Approved | F45: it-support@1pwrafrica.com | G45: Approved | H45: Solved. | I45: 06/22/2022 02:47:19
A46: 72 | C46: 06/23/2022 09:53:11 | D46: moeketse@1pwrafrica.com | E46: Approved | F46: it-support@1pwrafrica.com | G46: Approved | H46: Can attach a screenshot? | I46: 06/23/2022 10:09:37
A47: 73 | C47: 06/23/2022 09:57:30 | D47: moeketse@1pwrafrica.com | E47: In Progress | F47: it-support@1pwrafrica.com
A48: 74 | C48: 06/27/2022 08:29:52 | D48: makoetje@1pwrafrica.com | E48: In Progress | F48: it-support@1pwrafrica.com
A49: 75 | C49: 06/27/2022 14:23:11 | D49: morema@1pwrafrica.com | E49: In Progress | F49: it-support@1pwrafrica.com
A50: 76 | C50: 06/27/2022 15:17:13 | D50: ernestmoloantoateb@gmail.com | E50: In Progress | F50: it-support@1pwrafrica.com
A51: 77 | C51: 06/29/2022 06:05:59 | D51: mothomotsoanabk@gmail.com | E51: In Progress | F51: it-support@1pwrafrica.com
A52: 78 | C52: 06/29/2022 07:39:59 | D52: gabriellamorongwa@gmail.com | E52: In Progress | F52: it-support@1pwrafrica.com
A53: 79 | C53: 06/29/2022 08:54:52 | D53: neo@1pwrafrica.com | E53: In Progress | F53: it-support@1pwrafrica.com
A54: 80 | C54: 06/30/2022 15:07:52 | D54: lichabajameswest@gmail.com | E54: In Progress | F54: it-support@1pwrafrica.com
A55: 81 | C55: 44568.218 | D55: letseka@1pwrafrica.com | E55: In Progress | F55: it-support@1pwrafrica.com
A56: 82 | C56: 44658.329 | D56: kubutu@1pwrafrica.com | E56: In Progress | F56: it-support@1pwrafrica.com
A57: 83 | C57: 44658.426 | D57: makhoalinyane@1pwrafrica.com | E57: In Progress | F57: it-support@1pwrafrica.com
A58: 84 | C58: 44658.538 | D58: makhoalinyane@1pwrafrica.com | E58: In Progress | F58: it-support@1pwrafrica.com
A59: 85 | C59: 44688.286 | D59: makoetje@1pwrafrica.com | E59: In Progress | F59: it-support@1pwrafrica.com
A60: 86 | C60: 44688.287 | D60: monoane@1pwrafrica.com | E60: In Progress | F60: it-support@1pwrafrica.com
A61: 87 | C61: 44688.29 | D61: mokoatle@1pwrafrica.com | E61: In Progress | F61: it-support@1pwrafrica.com
A62: 88 | C62: 44688.292 | D62: monaheng@1pwrafrica.com | E62: In Progress | F62: it-support@1pwrafrica.com
A63: 89 | C63: 44688.292 | D63: mokoantle@1pwrafrica.com | E63: In Progress | F63: it-support@1pwrafrica.com
A64: 90 | C64: 44719.267 | D64: deon@1pwrafrica.com | E64: In Progress | F64: it-support@1pwrafrica.com
A65: 91 | C65: 44719.398 | D65: jonase@1pwrafrica.com | E65: In Progress | F65: it-support@1pwrafrica.com
A66: 92 | C66: 44749.266 | D66: palama@1pwrafrica.com | E66: Approved | F66: it-support@1pwrafrica.com | G66: Approved | I66: 44749.284
A67: 93 | C67: 44749.306 | D67: maferete@1pwrafrica.com | E67: In Progress | F67: it-support@1pwrafrica.com
A68: 94 | C68: 44780.35 | D68: deon@1pwrafrica.com | E68: Approved | F68: it-support@1pwrafrica.com | G68: Approved | I68: 44780.384
A69: 95 | C69: 44780.371 | D69: deon@1pwrafrica.com | E69: In Progress | F69: it-support@1pwrafrica.com
A70: 96 | C70: 44811.397 | D70: monoane@1pwrafrica.com | E70: In Progress | F70: it-support@1pwrafrica.com
A71: 97 | C71: 44811.847 | D71: leloko@1pwrafrica.com | E71: Approved | F71: it-support@1pwrafrica.com | G71: Approved | I71: 44872.33
A72: 98 | C72: 44872.249 | D72: deon@1pwrafrica.com | E72: In Progress | F72: it-support@1pwrafrica.com
A73: 99 | C73: 44872.307 | D73: mosoeunyanebotle@gmail.com | E73: Approved | F73: it-support@1pwrafrica.com | G73: Approved | H73: please come and get it at 10:10hrs | I73: 44872.33
A74: 100 | C74: 44872.348 | D74: mosoeunyanebotle@gmail.com | E74: In Progress | F74: it-support@1pwrafrica.com
A75: 101 | C75: 44872.348 | D75: deon@1pwrafrica.com | E75: In Progress | F75: it-support@1pwrafrica.com
A76: 102 | C76: 44872.377 | D76: serobanyane@1pwrafrica.com | E76: Approved | F76: it-support@1pwrafrica.com | G76: Approved | H76: Hey Neo, We currently do not have additional laptops in stock. We can get you an Ethernet to USB adaptor instead. We will make a purchase request today and hopefully buy it tomorrow. Regards, Morema | I76: 44872.457
A77: 103 | C77: 44872.516 | D77: ralefaso@1pwrafrica.com | E77: In Progress | F77: it-support@1pwrafrica.com
A78: 104 | C78: 44902.359 | D78: phoka@1pwrafrica.com | E78: Approved | F78: it-support@1pwrafrica.com | G78: Approved | H78: Hey Raphoka, Go to https://app.clickup.com/login and click on the "Forgot Password?" link. Please let me know if you still have issues. Regards, Morema | I78: 44902.37
A79: 105 | C79: 44902.471 | D79: josias@1pwrafrica.com | E79: Approved | F79: it-support@1pwrafrica.com | G79: Approved | I79: 44902.472
A80: 106 | C80: 44902.491 | D80: lichabajameswest@gmail.com | E80: Approved | F80: it-support@1pwrafrica.com | G80: Approved | H80: Sure, Ke tlo u fa eona. Morema | I80: 44902.075
A81: 107 | C81: 44902.624 | D81: deon@1pwrafrica.com | E81: Approved | F81: it-support@1pwrafrica.com | G81: Approved | H81: Noted, we are gonna have to get a mouse and then will give you those. | I81: 07/13/2022 09:39:22
A82: 108 | C82: 07/13/2022 10:05:55 | D82: thabo@1pwrafrica.com | E82: Approved | F82: it-support@1pwrafrica.com | G82: Approved | H82: m | I82: 07/13/2022 12:25:31
A83: 109 | C83: 07/13/2022 11:59:20 | D83: morema@1pwrafrica.com | E83: In Progress | F83: it-support@1pwrafrica.com
A84: 110 | C84: 07/14/2022 05:11:52 | D84: rethabile@1pwrafrica.com | E84: In Progress | F84: it-support@1pwrafrica.com
A85: 111 | C85: 07/14/2022 07:49:11 | D85: makhoalinyane@1pwrafrica.com | E85: In Progress | F85: it-support@1pwrafrica.com
A86: 112 | C86: 07/14/2022 09:48:32 | D86: gabriellamorongwa@gmail.com | E86: Approved | F86: it-support@1pwrafrica.com | G86: Approved | H86: Will bring it to you Mme. Regards, Motebang | I86: 07/14/2022 10:17:17
A87: 113 | C87: 07/14/2022 12:13:20 | D87: ernestmoloantoateb@gmail.com | E87: Approved | F87: it-support@1pwrafrica.com | G87: Approved | H87: Got it? Morema | I87: 07/14/2022 01:37:19
A88: 114 | C88: 07/15/2022 07:38:15 | D88: morema@1pwrafrica.com | E88: Approved | F88: it-support@1pwrafrica.com | G88: Approved | I88: 07/18/2022 07:01:58
A89: 115 | C89: 07/15/2022 14:01:27 | D89: serobanyane@1pwrafrica.com | E89: In Progress | F89: it-support@1pwrafrica.com
A90: 116 | C90: 07/18/2022 07:30:11 | D90: lichabajameswest@gmail.com | E90: Approved | F90: it-support@1pwrafrica.com | G90: Approved | I90: 07/18/2022 09:04:06
A91: 117 | C91: 07/18/2022 08:32:31 | D91: deon@1pwrafrica.com | E91: In Progress | F91: it-support@1pwrafrica.com
A92: 118 | C92: 07/18/2022 09:25:56 | D92: serobanyane@1pwrafrica.com | E92: Approved | F92: it-support@1pwrafrica.com | G92: Approved | H92: You can collect it from the EE Area. - Morema | I92: 07/18/2022 09:33:59
A93: 119 | C93: 07/19/2022 14:43:42 | D93: kekeletso@1pwrafrica.com | E93: Approved | F93: it-support@1pwrafrica.com | G93: Approved | H93: You can come and get it mme. Regards, Motebang | I93: 07/19/2022 03:09:42
A94: 120 | C94: 07/20/2022 15:00:45 | D94: deon@1pwrafrica.com | E94: Approved | F94: it-support@1pwrafrica.com | G94: Approved | H94: Hey Deon, We have updated the approver list. Regards, Morema | I94: 07/20/2022 03:41:37
A95: 121 | C95: 07/22/2022 06:52:25 | D95: moirema@1pwrafrica.com | E95: In Progress | F95: it-support@1pwrafrica.com
A96: 122 | C96: 07/22/2022 07:13:41 | D96: rasekeiti@1pwrafrica.com | E96: Approved | F96: it-support@1pwrafrica.com | G96: Approved | I96: 07/22/2022 07:32:32
A97: 123 | C97: 07/22/2022 07:33:16 | D97: rasekeiti@1pwrafrica.com | E97: Approved | F97: it-support@1pwrafrica.com | G97: Approved | H97: Your request is noted please hold on for sometime we have put the request to August budget | I97: 07/22/2022 07:44:09
A98: 124 | C98: 07/22/2022 09:03:10 | D98: maferete37@gmail.com | E98: In Progress | F98: it-support@1pwrafrica.com
A99: 125 | C99: 07/26/2022 10:32:31 | D99: deon@1pwrafrica.com | E99: In Progress | F99: it-support@1pwrafrica.com
A100: 126 | C100: 07/26/2022 11:07:30 | D100: deon@1pwrafrica.com | E100: In Progress | F100: it-support@1pwrafrica.com
...

Sheet Tickets
A1: Timestamp | B1: Email address | C1: Email Address | D1: Select your Department | E1: Priority | F1: Choose option you want to be helped on? | G1: Complaint Type | H1: Problem Description (e.g Laptop not connecting to the internet) | I1: Attachment (Optional) e.g Share a screenshot of the problem | J1: Item Requested | K1: What do you need for? | L1: Quantity | M1: Attachment (Optional) e.g Share a photo of items Checked out | N1: Full Names | O1: Respondent's Email Address | R1: Request # [DO NOT DELETE] | S1: Unique Request # [DO NOT DELETE] | T1: Unique Request # [DO NOT DELETE] | U1: Final Status [DO NOT DELETE] | V1: Final Status [DO NOT DELETE] | X1: Overall Status
A2: 44599.737 | C2: Kamohelo | D2: EE Department
A3: 44599.775 | B3: motebanglekhooana@gmail.com | C3: Motebang Lekhooana | D3: EE Department
A4: 44599.778 | B4: kamohelo0329@gmail.com | C4: Kamohelo Makaaka | D4: EE Department
A5: 44600.432 | B5: mohlomirasekeiti@gmail.com | C5: Rasekeiti Mohlomi | D5: Operations and Maintanance
A6: 44601.377 | B6: morema@1pwrafrica.com | C6: Morema Thabo Mafantiri | D6: EE Department
A7: 44601.493 | B7: motebanglekhooana@gmail.com | C7: Motebang Lekhooana | D7: EE Department | G7: Hardware, do not have a monitor also.
A8: 44608.378 | B8: motebanglekhooana@gmail.com | C8: Motebang Lekhooana | D8: EE Department | G8: VGA to HDMI Converter | H8: Would like to have the mentioned tool please
A9: 44608.385 | B9: lsmatsepe@gmail.com | C9: Lebalang Sophia Relebohile 'Makhotso Matsepe | D9: EE Department | G9: WIFI problem | H9: why do you hate me so, why can i never connect to the wifi? ha! Do i not deserve nice things also?
A10: 44609.352 | B10: lsmatsepe@gmail.com | C10: lebalang matsepe | D10: EE | G10: Tool Request | H10: I need MS office
A11: 44616.632 | B11: tums@1pwrafrica.com | C11: Tumelo Makhetha | D11: Project Management | G11: Email | H11: My 1pwr email only works when I'm logged in as a guest user on my chrome browser.
A12: 44617.666 | B12: david@1pwrafrica.com | C12: David Song | D12: Project Management | G12: Calendar | H12: When I get a calendar invite, I sometimes have an issue of a time showing up in my calendar that is different from the original sender's time. Also, this form should include a way to upload document. I could share an email that shows the issue or I could send a screen shot. Also, should you have a separate "department" for management?
A13: 44622.594 | B13: david@1pwrafrica.com | C13: David Song | D13: Project Management | G13: Calendar Time Zones | H13: Neo S sent me an invite shows in my outlook that it was set in Amman Jordan Time. But we checked his settings, and it's in Maseru time. Can you please check this? Our meeting is one hour off. I think maybe Moeketse changed the invite, and maybe that messed things up?
A14: 44623.428 | B14: david@1pwrafrica.com | C14: David Song | D14: Project Management | G14: Calendar | H14: I often get multiple responses to a calendar invite that I sent out. | I14: https://drive.google.com/open?id=1Nk0z0tde8cduNqGwj_qB2-6uqBLJkuUe
A15: 44624.419 | B15: phoka@1pwrafrica.com | C15: Phoka Raphoka | D15: Procurement | G15: Device Issue (laptop, tablet or mobile phone) | H15: I need to install Java & Asycuda World the LRA Portal that allows me to retrieve VAT 11 documents for all motor vehicles procured, I need admin login details on the laptop.
A16: 44627.502 | B16: palama@1pwrafrica.com | C16: Palama Kelepa | D16: Finance | G16: Email | H16: outlook error message: sending reported error (0x800CCC78), verify email in account properties: server responded: 452 space shortage, please try later
A17: 44641.526 | B17: serobanyane@1pwrafrica.com | C17: Neo Serobanyane | D17: Operations and Maintainance | G17: Device Issue (laptop, tablet or mobile phone) | H17: SMS gateway not functional, customers complain that when they sent call back to check their balance they don't get their balance and they say it's been a while now.
A18: 44641.528 | B18: serobanyane@1pwrafrica.com | C18: Neo Serobanyane | D18: Operations and Maintainance | G18: Device Issue (laptop, tablet or mobile phone) | H18: SMS gateway not functional. M-Pesa messages appear on the App but SMS gateway doesn't automatically credit customers as usual.
A19: 44641.53 | B19: serobanyane@1pwrafrica.com | C19: Neo Serobanyane | D19: Operations and Maintainance | G19: Device Issue (laptop, tablet or mobile phone) | H19: Some m-pesa transactions date and time on SMS gateway invalid and gateway not crediting customers.
A20: 44649.426 | B20: tums@1pwrafrica.com | C20: Tumelo | D20: Project Management | G20: Internet Issue | H20: Very very poor connectivity yesterday and today
A21: 44663.679 | B21: phoka@1pwrafrica.com | C21: Phoka Raphoka | D21: Procurement | G21: Email | H21: I am unable to send email they bounce back with the following message: "This message was created automatically by mail delivery software. A message that you sent could not be delivered to one or more of its recipients. This is a permanent error. The following address(es) failed: Domain 1pwrafrica.com has exceeded the max defers and failures per hour (150/150 (92%)) allowed. Message discarded"
A22: 44670.586 | B22: teboho@1pwrafrica.com | C22: TEBOHO NOKO | D22: Reticulation | G22: Email | H22: can not login to my emails, Screenshot attached | I22: https://drive.google.com/open?id=10MhZyDLQ3wml9LuB9ykhQ91TLoUWuOJr
A23: 44671.667 | B23: motebanglekhooana@gmail.com | C23: Motebang Lekhooana | D23: EE | F23: Complaint Ticket | G23: Device Issue (laptop, tablet or mobile phone) | H23: test
A24: 44671.669 | B24: motebanglekhooana@gmail.com | F24: Budget Request | J24: test | K24: test
A25: 44671.711 | B25: motebanglekhooana@gmail.com | F25: Budget Request | J25: test | K25: test
A26: 44672.486 | B26: cadkikine@gmail.com | C26: Cad | D26: EE | F26: Budget Request | J26: Charger | K26: Test
A27: 44672.594 | B27: cadkikine@gmail.com | C27: Tlhoks | D27: EE | F27: Budget Request | J27: test | K27: test
A28: 44672.609 | B28: cadkikine@gmail.com | C28: Test | D28: EE | F28: Complaint Ticket | G28: Test | H28: Test
A29: 44672.665 | B29: test@gmail.com | C29: Test | D29: Finance | F29: Budget Request | J29: Test | K29: Testing
A30: 44677.659 | B30: morema@1pwrafrica.com | C30: Morema | D30: EE | F30: Equipment Request | J30: mouse | K30: hakena mouse
A31: 44692.389 | B31: motebanglekhooana@gmail.com | C31: Motebang | D31: EE | F31: Equipment Request | J31: test | K31: test
A32: 44694.655 | B32: h@gmail.com | C32: Jos | D32: Finance | E32: High | F32: Equipment Request | J32: mouse | K32: testing
A33: 44699.345 | B33: deon@1pwrafrica.com | C33: Deon | D33: Production | E33: Medium | F33: Report Issue | G33: Clockify / HR Portal | H33: Please assist Kubutu using HR Portal to submit his timecards. The problem seems to be with OT, remarks and exceptions. He was unable to submit timecards for April and still can't submit for May. | I33: https://drive.google.com/open?id=1QoU3gPP-iIragUSSWaIUPcIm-uOtNsk3, https://drive.google.com/open?id=1OwKrAvkCaTZ_g7mh3E5WHblBWc0wF9hL
A34: 44699.458 | B34: deon@1pwrafrica.com | C34: Deon | D34: Production | E34: Medium | F34: Report Issue | G34: Internet Issue | H34: 1PWR2 Wifi in Production area had no internet access yesterday and today its not available at all.
A35: 44700.403 | B35: deon@1pwrafrica.com | C35: Deon | D35: Production | E35: Medium | F35: Report Issue | G35: Internet Issue | H35: Follow up on ticket #23 which was not solved as reported. Still no internet access. | I35: https://drive.google.com/open?id=1Sqg7lAWPi03A3yFZVM2uUVIRJ55ARDoa
A36: 44700.621 | B36: deon@1pwrafrica.com | C36: Deon | D36: Production | E36: Medium | F36: Report Issue | G36: Internet Issue | H36: 1PWR2 connection only worked for about one hour after Econet service. No internet access available currently.
A37: 44700.743 | B37: tums@1pwrafrica.com | C37: Tumelo | D37: Project Management | E37: High | F37: Equipment Request | J37: Laptop | K37: Everyday work for Mlanjeni. His personal laptop's performance is deteriorating by the week.
A38: 44701.561 | B38: david@1pwrafrica.com | C38: David Song | D38: Project Management | E38: Low | F38: Report Issue | G38: Web site | H38: the O&M JD link is broken (https://1pwrafrica.com/?post_type=job_listing&p=3235); also does this form need to be two pages?
A39: 44711.604 | B39: tumelo@1pwrafrica.com | C39: Tumelo | D39: Project Management | E39: Medium | F39: Report Issue | G39: Email | H39: When I open my email to log in, I a message saying: " Your connection is not private". A screen shot of the message is attached. | I39: https://drive.google.com/open?id=1By_JccXQUuHSiTEEvEtnPu3hwcCvbraP
A40: 44712.473 | B40: cadkikine@gmail.com | C40: cad | D40: EE | E40: Low | F40: Equipment Request | J40: Tablet | K40: test | R40: 30 | V40: Approved
A41: 44712.475 | B41: cadkikine@gmail.com | C41: cad | D41: Operations and Maintenance | E41: High | F41: Equipment Request | J41: Phone | K41: test | R41: 31 | V41: In Progress
A42: 44712.476 | B42: cadkikine@gmail.com | C42: cad | D42: Project Management | E42: Medium | F42: Equipment Request | J42: Monitor | K42: test | R42: 32 | V42: In Progress
A43: 44718.401 | B43: makhoalinyane@1pwrafrica.com | C43: Teboho | D43: Reticulation | E43: Low | F43: Equipment Request | J43: Laptop | K43: Map reviewing, on boarding and tool training | R43: 33 | V43: Approved
A44: 44718.406 | B44: mosehle@1pwrafrica.com | C44: Mosehle mokoatle | D44: Reticulation | E44: Low | F44: Equipment Request | J44: Laptop | K44: On boarding training | R44: 34 | V44: In Progress
A45: 44718.41 | B45: kubutu@1pwrafrica.com | C45: Kubutu Makhakhe | D45: Production | E45: High | F45: Report Issue | G45: Clockify / HR Portal | H45: Not being able to submit my time cards | R45: 35 | V45: In Progress
A46: 44718.417 | B46: ernestmoloantoateb@gmail.com | C46: Teboho Moloantoa | D46: Project Management | E46: High | F46: Equipment Request | J46: Laptop, Monitor | K46: For daily execution of PM tasks at HQ and when on-site. My personal laptop's screen is cracked, this unfortunate incident therefore subsequently hinders the progress and ease of work done. | R46: 36 | V46: In Progress
A47: 44718.458 | B47: monoane@1pwrafrica.com | C47: Sello Monoane | D47: Reticulation | E47: High | F47: Report Issue | G47: Device Issue (laptop, tablet or mobile phone) | H47: Laptop has a problem of launching dropbox desktop app. RET006 It loads and then nothing. | R47: 37 | V47: In Progress
A48: 44718.688 | B48: leloko@1pwrafrica.com | C48: Leloko Monese | D48: Reticulation | F48: Equipment Request | J48: Photo of items checked out | K48: Site to Tosing | L48: Photo will show | M48: https://drive.google.com/open?id=1wEIgGDN-QIxwWPes0HCJHpr-wy9MJ2nT | R48: 38 | V48: In Progress | W48: multiplug not returned
A49: 44718.696 | B49: makhoalinyane@1pwrafrica.com | C49: Teboho | D49: Reticulation | F49: Equipment Request | J49: Photo will show | K49: Sebapala Trip | L49: Photo will show | M49: https://drive.google.com/open?id=1RdQWielMsC66Rsecugehif4nbe-tkpXq | R49: 39 | V49: In Progress | W49: Returned
A50: 44718.711 | B50: mosehle@1pwrafrica.com | C50: Mokoatle | D50: Reticulation | F50: Equipment Request | J50: Photo will explain | K50: Matsoing | L50: Photo will explain | M50: https://drive.google.com/open?id=1hRM8F_Q0uwYEeIDxAbsv46Xnn83muF6u | R50: 40 | V50: In Progress
A51: 44719.395 | B51: makoetje@1pwrafrica.com | C51: Lebusa Makoetje | D51: Reticulation | F51: Equipment Request | J51: Photo will show | K51: Tlhanyaku | L51: Photo will explain | M51: https://drive.google.com/open?id=1B7YTk8fq-X_OJdTMJTWSV5AGd3Ww92n5 | R51: 41 | V51: Approved
A52: 44719.484 | B52: jopi@1pwrafrica.com | C52: Leoma Jopi | D52: Reticulation | F52: Equipment Request | J52: Laptop | K52: Casual contact drafting | L52: 1 | R52: 42 | V52: Approved
A53: 44719.525 | B53: moeketse@1pwrafrica.com | C53: Moeketse Kuenane | D53: Operations and Maintainance | F53: Report Issue | G53: Device Issue (laptop, tablet or mobile phone) | H53: Smart Kicka 5 Plus screen broken | R53: 43 | V53: Approved
A54: 44719.613 | B54: jonase@1pwrafrica.com | C54: JONASE NTHUNYA | D54: EHS | F54: Equipment Request | J54: Tablet | K54: Mashai & Sehonghong SITE Visit | L54: 1 | R54: 44 | V54: Approved
A55: 44720.392 | B55: david@1pwrafrica.com | C55: David Song | D55: Project Management | F55: Report Issue | G55: PR Form | H55: Is there a way to improve the attachment view? Right now, I have to download the Excel files because they're not completely legible when following the link. | R55: 45 | V55: In Progress
A56: 44720.398 | B56: lichabajameswest@gmail.com | C56: Lichaba West | D56: EE | F56: Equipment Request | J56: Laptop | K56: With the desktop I use, whenever the elecricity goes down I lose all my current work. | L56: 1 | R56: 46 | V56: Approved
A57: 44720.701 | B57: mothomotsoanabk@gmail.com | C57: Bokang Mothomotsoana | D57: EE | F57: Equipment Request | J57: back up rooter | K57: Backup router | L57: 1 | R57: 47 | V57: Approved
A58: 44721.475 | B58: mlanjenijoshua@gmail.com | C58: Mlanjeni Tikiso | D58: Project Management | F58: Equipment Request | J58: Laptop, Extension cord | K58: Laptop for work. Extension cord for extending socket for heater | L58: 1 | R58: 48 | V58: In Progress
A59: 44722.411 | B59: abele@1pwrafrica.com | C59: Abele Mahao | D59: Fleet | F59: Equipment Request | J59: Power Bank | K59: Going to Haramabanta and my phone is off | L59: 1 | R59: 49 | V59: Approved
A60: 44722.584 | B60: phoka@1pwrafrica.com | C60: PhokaRaphoka | D60: Procurement | F60: Report Issue | G60: Device Issue (laptop, tablet or mobile phone) | H60: Need a screen replacement on the mobile phone I am using(Com 03) it is cracked | R60: 50 | V60: Approved
A61: 44725.342 | B61: thakhisinthabiseng@gmail.com | C61: Nthabiseng Thakhisi | D61: Project Management | F61: Equipment Request | J61: EXtension cord | K61: heater plug | L61: 1 | R61: 51 | V61: Approved
A62: 44725.488 | B62: maferete@1pwrafrica.com | C62: Maferete Moorosi | D62: EHS | F62: Report Issue | G62: Device Issue (laptop, tablet or mobile phone) | H62: screen needs to be replaced | R62: 52 | V62: Rejected
A63: 44725.506 | B63: lichabajameswest@gmail.com | C63: Lichaba West | D63: EE | F63: Report Issue | G63: Device Issue (laptop, tablet or mobile phone) | H63: Mouse stopped working | R63: 53 | V63: In Progress
A64: 44725.526 | B64: morema@1pwrafrica.com | C64: Morema | D64: EE | F64: Equipment Request | J64: locker keys | K64: To have access to the maps and IT lockers | L64: 2 | R64: 54 | V64: In Progress
A65: 44725.528 | B65: morema@1pwrafrica.com | C65: Morema | D65: EE | F65: Report Issue | G65: Device Issue (laptop, tablet or mobile phone) | H65: The USB-C to HMDI adaptor is no longer working. | R65: 55 | V65: Approved
A66: 44725.535 | B66: phoka@1pwrafrica.com | C66: Phoka Raphoka | D66: Procurement | F66: Equipment Request | J66: Phone | K66: Temporary phone while the one assigned to me is taken for repairs. | L66: 1 | R66: 56 | V66: In Progress
A67: 44725.539 | B67: phoka@1pwrafrica.com | C67: Phoka Raphoka | D67: Procurement | F67: Report Issue | G67: Device Issue (laptop, tablet or mobile phone) | H67: Phone assigned to me accidentally fell and cracked the screen on the top right corner, a request for repairs has been sent out and is approved. | R67: 57 | V67: In Progress
A68: 44725.557 | B68: cadkikine@gmail.com | C68: testing | D68: EE | F68: Report Issue | G68: testing | H68: test | I68: https://drive.google.com/open?id=13s_KoPyV6OrdlcD01DyTgeyn8CmPW3fT | R68: 58 | V68: In Progress
A69: 44725.716 | B69: makoetje@1pwrafrica.com | C69: Lebusa Makoetje | D69: Reticulation | F69: Report Issue | G69: Clockify / HR Portal | H69: HR portal doesn't allow me to edit the card that have to be revised and resubmitted. | I69: https://drive.google.com/open?id=1jASQG81zkL9wJd7NDLjCVnWbIRWqVNPi, https://drive.google.com/open?id=1HvIB6xn-AkW7e5nVwfraVl6tuAbRRmP7 | R69: 59 | V69: In Progress
A70: 44726.399 | B70: morema@1pwrafrica.com | C70: Morema Mafantiri | D70: Project Management | F70: Equipment Request | J70: Multiplug adaptor | K70: To connect my monitor, laptop, phone charger and monitor | L70: 1 | R70: 60 | V70: In Progress
A71: 44726.404 | B71: Ramatla@1pwrafrica.com | C71: Ts'episo Ramatla | D71: Reticulation | F71: Report Issue | G71: Clockify / HR Portal | H71: I have to revise and resubmit timecard and no option for edit and submi on timecard. I need help on there.. | I71: https://drive.google.com/open?id=1K6lACKHivnMIvlzIHYu5MhbjjfjBNaWR, https://drive.google.com/open?id=1c1kGefG2ymwosPdkzXPR9yN5gk-LvPwR | R71: 61 | V71: In Progress
A72: 44726.49 | B72: molefe@1pwrafrica.com | C72: Molefe motebang | D72: Fleet | F72: Report Issue | G72: I want to change my one power email password....ever since I was given it, I wasn't able to log in | H72: My one power email not active; am not able to use it due to invalid password | R72: 62 | V72: Approved
A73: 44727.65 | B73: lichabajameswest@gmail.com | C73: Lichaba West | D73: EE | F73: Equipment Request | J73: Laptop | K73: Work from home to update TOS on uGridPLAN as the power tripping at work keeps causing me to lose work | L73: 1 | R73: 63 | V73: Approved
A74: 44727.654 | B74: tkemathaba@gmail.com | C74: Tumisang Mathaba | D74: EE | F74: Equipment Request | J74: internet | K74: internet connection on overtime | L74: M25 | R74: 64 | V74: Rejected
A75: 44729.392 | B75: monoane@1pwrafrica.com | C75: Sello Monoane | D75: Reticulation | F75: Report Issue | G75: Device Issue (laptop, tablet or mobile phone) | H75: The laptop can't open Excel, it needs password for office to login. | I75: https://drive.google.com/open?id=14zkFvWfbAPa-9yxmL_pMKiO6cXGZJjNI | R75: 65 | V75: Approved
A76: 44729.417 | B76: monoane@1pwrafrica.com | C76: Sello Monoane | D76: Reticulation | F76: Report Issue | G76: uGrid Plan | H76: The Tool does not save the changes when i update and export the SHG SC file. The changes made are discarded after I export and reopen the file. | R76: 66 | V76: Approved
A77: 44729.448 | B77: mothomotsoanabk@gmail.com | C77: Bokang Mothomotsoana | D77: EE | F77: Report Issue | G77: Internet Issue | H77: The internet keep on cutting so I cant follow up the problem I want to solve for RIB offset properly | R77: 67 | V77: Approved
A78: 44729.463 | B78: phoka@1pwrafrica.com | C78: Phoka Raphoka | D78: Procurement | F78: Equipment Request | J78: Laptop, Mouse Pad | K78: I need a mouse pad for use on my desktop. | L78: 1 | R78: 68 | V78: Approved
A79: 44732.499 | B79: mothomotsoanabk@gmail.com | C79: Bokang Mothomotsoana | D79: EE | F79: Equipment Request | J79: modem | K79: Wifi connection | L79: 1 | R79: 69 | V79: Approved
A80: 44733.643 | B80: david@1pwrafrica.com | C80: David Song | D80: Project Management | F80: Report Issue | G80: Google forms | H80: Can you please make the email address on all google forms a drop down? I pretty regularly get typos, and then I have to forward the approval email or tell them something has been approved. It would save some time for the requestor as well. | R80: 70 | V80: Approved
A81: 44734.683 | B81: lichabajameswest@gmail.com | C81: Lichaba West | D81: EE | F81: Report Issue | G81: Device Issue (laptop, tablet or mobile phone) | H81: Desktop won't start up. Tried it twice the on third time it | R81: 71 | V81: Approved
A82: 44735.495 | B82: moeketse@1pwrafrica.com | C82: Moeketse Kuenane | D82: Operations and Maintenance | F82: Report Issue | G82: Email | H82: I'm facing a problem with replying my emails. Getting attached error message reporting to be a SPAM message. | I82: https://drive.google.com/open?id=1TjIhTtuMANt33xO2tXwSNeccAUm-x8zp | R82: 72 | V82: Approved
A83: 44735.498 | B83: moeketse@1pwrafrica.com | C83: Moeketse Kuenane | D83: Operations and Maintenance | F83: Equipment Request | J83: Monitor | K83: To monitor the sites and do the payments reconciliation. Rasekeiti and I don't have monitors. The TV's that we used before seem to be affecting our eyes hence the request to have access to the monitors. | L83: 2 | R83: 73 | V83: In Progress
A84: 44739.437 | B84: makoetje@1pwrafrica.com | C84: Lebusa Makoetje | D84: Reticulation | F84: Report Issue | G84: Device Issue (laptop, tablet or mobile phone) | H84: Laptop charger break up | I84: https://drive.google.com/open?id=1qisSzxAjebEpiJSPOAmLWxNSh3oGwwo- | R84: 74 | V84: In Progress
A85: 44739.683 | B85: morema@1pwrafrica.com | C85: Morema Mafantiri | D85: EE | F85: Report Issue | G85: Email | H85: my emails to Gmail addresses are failing | I85: https://drive.google.com/open?id=1-ibTcmOoxe9gqjWsrRYmuyCOCCrWeVvd | R85: 75 | V85: In Progress
A86: 44739.72 | B86: ernestmoloantoateb@gmail.com | C86: Teboho Moloantoa | D86: Project Management | F86: Equipment Request | J86: Monitor | K86: For work. I was borrowed Neo's monitor, he said he'll be back before the end of the week and he will need it back. | L86: 1 | R86: 76 | V86: In Progress
A87: 44741.337 | B87: mothomotsoanabk@gmail.com | C87: Bokang Mothomotsoana | D87: EE | F87: Equipment Request | J87: Monitor | K87: Working with maps and networks | L87: 2 | R87: 77 | V87: In Progress
A88: 44741.403 | B88: gabriellamorongwa@gmail.com | C88: Morongwa Saku | D88: Project Management | F88: Equipment Request | J88: Mouse | K88: Use as an input device | L88: 1 | R88: 78 | V88: In Progress
A89: 44741.455 | B89: neo@1pwrafrica.com | C89: Neo Makosholo | D89: Reticulation | F89: Equipment Request | J89: Monitor | K89: Commission report | L89: 1 | R89: 79 | V89: In Progress
A90: 44742.714 | B90: lichabajameswest@gmail.com | C90: Lichaba West | D90: EE | F90: Report Issue | G90: Dropbox | H90: Eng folder is accessible by only ee even though we are not the primary users of this folder. Possibly there has been a split somewhere where there is a proper ENG folder and a "fake" ee ENG folder floating around Dropbox | R90: 80 | V90: In Progress
A91: 44743.301 | B91: letseka@1pwrafrica.com | C91: Taole Letseka | D91: Reticulation | F91: Equipment Request | J91: Laptop, Tablet, Phone, Modem, invertor | K91: Work | L91: 6 | M91: https://drive.google.com/open?id=1VAe39IPAqJHldqbmbXPsCFC-rL7amcqT | R91: 81 | V91: In Progress
A92: 44746.413 | B92: kubutu@1pwrafrica.com | C92: Kubutu makhakhe | D92: Production | F92: Report Issue | G92: Device Issue (laptop, tablet or mobile phone) | H92: Dropbox | R92: 82 | V92: In Progress
A93: 44746.51 | B93: makhoalinyane@1pwrafrica.com | C93: Teboho Makhoalinane | D93: Reticulation | F93: Equipment Request | J93: Laptop, Chargeer, mouse | K93: Map viewing | L93: 1 | R93: 83 | V93: In Progress
A94: 44746.621 | B94: makhoalinyane@1pwrafrica.com | C94: Mokhethi Komete | D94: Reticulation | F94: Equipment Request | J94: Laptop | K94: SEB | L94: 1 | M94: https://drive.google.com/open?id=1E17A2OgEl-P-Kujnqeftvbf9Nb-_ykHm | R94: 84 | V94: In Progress
A95: 44747.37 | B95: makoetje@1pwrafrica.com | C95: Lebusa Makoetje | D95: Reticulation | F95: Equipment Request | J95: Laptop | K95: For TLH | L95: 1 | M95: https://drive.google.com/open?id=1AEIBMrUGZeHpYsORzSSpXiUhzo0G8VbF | R95: 85 | V95: In Progress
A96: 44747.37 | B96: monoane@1pwrafrica.com | C96: Sello Monoane | D96: Reticulation | F96: Equipment Request | J96: Laptop, USB CABLE, SOLAR CHARGER,laptop charger | K96: Work | L96: 1 | M96: https://drive.google.com/open?id=1mU0UVtVWyGhRAapnSkmDkTGjcifPv_rw | R96: 86 | V96: In Progress
A97: 44747.373 | B97: mokoatle@1pwrafrica.com | C97: Mokoatle Mokoatle | D97: Reticulation | F97: Equipment Request | J97: Laptop, Mouse,USB CABLE,solar charger,laptop charger | K97: Work | L97: 1 | M97: https://drive.google.com/open?id=1-zgD5IUdb5aerYeTwE-ZDksiLZsuiu8b | R97: 87 | V97: In Progress
A98: 44747.375 | B98: monaheng@1pwrafrica.com | C98: Rethabile Monaheng | D98: Reticulation | F98: Equipment Request | J98: Laptop | K98: Working at site | L98: 4 | M98: https://drive.google.com/open?id=10amT3OiML6sYOcyHOsCURybLPGb-Brs8 | R98: 88 | V98: In Progress | W98: Solar charger returned
A99: 44747.376 | B99: mokoantle@1pwrafrica.com | C99: Mokoatle Mokoatle | D99: Reticulation | F99: Equipment Request | J99: Laptop, Mouse,laptop charger,usb cable,solar charger | K99: Work | L99: 1 | M99: https://drive.google.com/open?id=1YJ77fCrj0AgsfVE4rdWSjNUEoaijEvJU | R99: 89 | V99: In Progress
A100: 44748.35 | B100: deon@1pwrafrica.com | C100: Deon | D100: Production | F100: Report Issue | G100: Internet Issue | H100: No internet access at workshop mezzanine area. | R100: 90 | V100: In Progress
...

Sheet Sheet11

Sheet Check out
A1: Timestamp | B1: Company ID | C1: Equipment Description | D1: Checked By | E1: Entry Number | F1: Counter in check in | G1: Availabilty State | H1: =Inventory!B:B -> Company ID
H2: =Inventory!B:B
H3: =Inventory!B:B -> OnM Deparment Desktop
H4: =Inventory!B:B -> LOG01
A5: 44727.381 | B5: Main 0374 | C5: Phone | D5: Phoka Raphoka | E5: 1 | F5: =countif('Check in'!B:B,B5) -> 1 | G5: =ifs(exact(E5,F5),"Available",F5>E5,"Check item out first",E5>F5,"Checked out") -> Available | H5: =Inventory!B:B -> LOG02
A6: 44727.383 | B6: Com 01 | C6: Committee phone | D6: Tumelo Makhakhe | E6: =countif(B:B,B6) -> 1 | F6: =countif('Check in'!B:B,B6) -> 1 | G6: =ifs(exact(E6,F6),"Available",F6>E6,"Check item out first",E6>F6,"Checked out") -> Available | H6: =Inventory!B:B -> LOG03
A7: 44727.386 | B7: Com 02 | C7: Committee phone | D7: Mongali Tlali | E7: =countif(B:B,B7) -> 1 | F7: =countif('Check in'!B:B,B7) -> 0 | G7: =ifs(exact(E7,F7),"Available",F7>E7,"Check item out first",E7>F7,"Checked out") -> Checked out | H7: =Inventory!B:B -> LOG04
A8: 44727.387 | B8: Com 03 | C8: Committee phone | D8: Phoka Raphoka | E8: =countif(B:B,B8) -> 1 | F8: =countif('Check in'!B:B,B8) -> 0 | G8: =ifs(exact(E8,F8),"Available",F8>E8,"Check item out first",E8>F8,"Checked out") -> Checked out | H8: =Inventory!B:B -> CHR01
A9: 44727.388 | B9: PMTEAM01 | C9: Laptop, Asus VivoBook X515JAB_X515JA | D9: Tumelo Makhakhe | E9: =countif(B:B,B9) -> 1 | F9: =countif('Check in'!B:B,B9) -> 0 | G9: =ifs(exact(E9,F9),"Available",F9>E9,"Check item out first",E9>F9,"Checked out") -> Checked out | H9: =Inventory!B:B -> CHR02
A10: 44727.389 | B10: PMTEAM02 | C10: Laptop, Asus VivoBook X515JAB_X515JA | D10: Mongali Tlali | E10: =countif(B:B,B10) -> 1 | F10: =countif('Check in'!B:B,B10) -> 0 | G10: =ifs(exact(E10,F10),"Available",F10>E10,"Check item out first",E10>F10,"Checked out") -> Checked out | H10: =Inventory!B:B -> CHR03
A11: 44727.39 | B11: EHS01 | C11: Laptop, Gateway GWTN156-1RG | D11: Maferete Moorosi | E11: =countif(B:B,B11) -> 1 | F11: =countif('Check in'!B:B,B11) -> 0 | G11: =ifs(exact(E11,F11),"Available",F11>E11,"Check item out first",E11>F11,"Checked out") -> Checked out | H11: =Inventory!B:B -> CHRO4
A12: 44727.393 | B12: EE001 | C12: Laptop, Dell Latitude | D12: Josias Molomo | E12: =countif(B:B,B12) -> 1 | F12: =countif('Check in'!B:B,B12) -> 0 | G12: =ifs(exact(E12,F12),"Available",F12>E12,"Check item out first",E12>F12,"Checked out") -> Checked out | H12: =Inventory!B:B -> KB01
A13: 44727.393 | B13: EE002 | C13: Laptop, Dell Latitude | D13: Thabo Monoto | E13: =countif(B:B,B13) -> 1 | F13: =countif('Check in'!B:B,B13) -> 0 | G13: =ifs(exact(E13,F13),"Available",F13>E13,"Check item out first",E13>F13,"Checked out") -> Checked out | H13: =Inventory!B:B -> KB02
A14: 44727.394 | B14: EE003 | C14: Laptop, Hp Elitebook 840 G3 | D14: Bokang Mothomotsoana | E14: =countif(B:B,B14) -> 1 | F14: =countif('Check in'!B:B,B14) -> 0 | G14: =ifs(exact(E14,F14),"Available",F14>E14,"Check item out first",E14>F14,"Checked out") -> Checked out | H14: =Inventory!B:B -> KB03
A15: 44727.395 | B15: EE004 | C15: Laptop, Dell Latitude | D15: Tumisang Mathaba | E15: =countif(B:B,B15) -> 1 | F15: =countif('Check in'!B:B,B15) -> 0 | G15: =ifs(exact(E15,F15),"Available",F15>E15,"Check item out first",E15>F15,"Checked out") -> Checked out | H15: =Inventory!B:B -> KB04
A16: 44727.396 | B16: EE005 | C16: Laptop, Dell Latitude | D16: Motebang Lekhooana | E16: =countif(B:B,B16) -> 1 | F16: =countif('Check in'!B:B,B16) -> 0 | G16: =ifs(exact(E16,F16),"Available",F16>E16,"Check item out first",E16>F16,"Checked out") -> Checked out | H16: =Inventory!B:B -> CP01
A17: 44727.399 | B17: 0080 | C17: Monitor, Hikvision | D17: Finance office | E17: =countif(B:B,B17) -> 1 | F17: =countif('Check in'!B:B,B17) -> 0 | G17: =ifs(exact(E17,F17),"Available",F17>E17,"Check item out first",E17>F17,"Checked out") -> Checked out | H17: =Inventory!B:B -> CP02
H18: =Inventory!B:B -> CP03
A19: 44727.404 | B19: AD002 | C19: Monitor,Telefunken TLEDD-24HD | D19: Refiloe Ramalefane | E19: =countif(B:B,B19) -> 1 | F19: =countif('Check in'!B:B,B19) -> 0 | G19: =ifs(exact(E19,F19),"Available",F19>E19,"Check item out first",E19>F19,"Checked out") -> Checked out | H19: =Inventory!B:B -> CP04
A20: 44727.404 | B20: AD003 | C20: Monitor, Telefunken TLEDD-24HD | D20: Moliehi Lepheane | E20: =countif(B:B,B20) -> 1 | F20: =countif('Check in'!B:B,B20) -> 0 | G20: =ifs(exact(E20,F20),"Available",F20>E20,"Check item out first",E20>F20,"Checked out") -> Checked out | H20: =Inventory!B:B -> LDS00
A21: 44727.406 | B21: EE01 | C21: Monitor, Dell S2421HN | D21: Josias Molomo | E21: =countif(B:B,B21) -> 1 | F21: =countif('Check in'!B:B,B21) -> 0 | G21: =ifs(exact(E21,F21),"Available",F21>E21,"Check item out first",E21>F21,"Checked out") -> Checked out | H21: =Inventory!B:B -> RBP00
A22: 44727.416 | B22: EE02 | C22: Monitor, Dell S2421HN | D22: Motlatsi Manka | E22: =countif(B:B,B22) -> 1 | F22: =countif('Check in'!B:B,B22) -> 0 | G22: =ifs(exact(E22,F22),"Available",F22>E22,"Check item out first",E22>F22,"Checked out") -> Checked out | H22: =Inventory!B:B -> SML001
A23: 44727.417 | B23: EE03 | C23: Monitor, Dell S2421HN | D23: Bokang Mothomotsoana | E23: =countif(B:B,B23) -> 1 | F23: =countif('Check in'!B:B,B23) -> 0 | G23: =ifs(exact(E23,F23),"Available",F23>E23,"Check item out first",E23>F23,"Checked out") -> Checked out | H23: =Inventory!B:B -> SML002
A24: 44727.42 | B24: EE04 | C24: Monitor, Samsung | D24: Tumisang Mathaba | E24: =countif(B:B,B24) -> 1 | F24: =countif('Check in'!B:B,B24) -> 0 | G24: =ifs(exact(E24,F24),"Available",F24>E24,"Check item out first",E24>F24,"Checked out") -> Checked out | H24: =Inventory!B:B -> SML003
A25: 44727.424 | B25: EE05 | C25: Monitor, Dell S2421HN | D25: Motebang Lekhooana | E25: =countif(B:B,B25) -> 1 | F25: =countif('Check in'!B:B,B25) -> 0 | G25: =ifs(exact(E25,F25),"Available",F25>E25,"Check item out first",E25>F25,"Checked out") -> Checked out | H25: =Inventory!B:B -> SML004
A26: 44727.424 | B26: EE06 | C26: Monitor, Dell S2421HN | D26: Thabang Hatlane | E26: =countif(B:B,B26) -> 1 | F26: =countif('Check in'!B:B,B26) -> 0 | G26: =ifs(exact(E26,F26),"Available",F26>E26,"Check item out first",E26>F26,"Checked out") -> Checked out | H26: =Inventory!B:B -> SML 005
A27: 44727.425 | B27: EE07 | C27: Monitor, Dell S2421HN | D27: Morema Mafantiri | E27: =countif(B:B,B27) -> 1 | F27: =countif('Check in'!B:B,B27) -> 0 | G27: =ifs(exact(E27,F27),"Available",F27>E27,"Check item out first",E27>F27,"Checked out") -> Checked out | H27: =Inventory!B:B -> PMP001
A28: 44727.426 | B28: EE08 | C28: Monitor, Samsung | D28: Lichaba West | E28: =countif(B:B,B28) -> 1 | F28: =countif('Check in'!B:B,B28) -> 0 | G28: =ifs(exact(E28,F28),"Available",F28>E28,"Check item out first",E28>F28,"Checked out") -> Checked out | H28: =Inventory!B:B -> BULB001
A29: 44727.426 | B29: EE09 | C29: Monitor, ViewSonic | D29: Tsabalira Phoofolo | E29: =countif(B:B,B29) -> 1 | F29: =countif('Check in'!B:B,B29) -> 0 | G29: =ifs(exact(E29,F29),"Available",F29>E29,"Check item out first",E29>F29,"Checked out") -> Checked out | H29: =Inventory!B:B -> Untagged/None
A30: 44727.427 | B30: 0444 | C30: Monitor, Telefunken | D30: O&M | E30: =countif(B:B,B30) -> 2 | F30: 1 | G30: =ifs(exact(E30,F30),"Available",F30>E30,"Check item out first",E30>F30,"Checked out") -> Checked out | H30: =Inventory!B:B -> Surf -1
A31: 44727.427 | B31: 0420 | C31: Monitor, Telefunken | D31: Neo Serobanyane | E31: =countif(B:B,B31) -> 2 | F31: =countif('Check in'!B:B,B31) -> 1 | G31: =ifs(exact(E31,F31),"Available",F31>E31,"Check item out first",E31>F31,"Checked out") -> Checked out | H31: =Inventory!B:B -> Main
A32: 44727.429 | B32: 0381-B | C32: Monitor, ViewSonic | D32: Jonas Nthunya | E32: =countif(B:B,B32) -> 2 | F32: =countif('Check in'!B:B,B32) -> 1 | G32: =ifs(exact(E32,F32),"Available",F32>E32,"Check item out first",E32>F32,"Checked out") -> Checked out | H32: =Inventory!B:B -> X-trail Phone
A33: 44727.435 | B33: AD001 | C33: Monitor, Dell S2421HN | D33: Palama Kelepa | E33: =countif(B:B,B33) -> 1 | F33: =countif('Check in'!B:B,B33) -> 0 | G33: =ifs(exact(E33,F33),"Available",F33>E33,"Check item out first",E33>F33,"Checked out") -> Checked out | H33: =Inventory!B:B -> Truck 36 Phone
A34: 44727.436 | B34: EHS-10 | C34: Monitor, Dell S2421HN | D34: Kekeletso Rakoti | E34: =countif(B:B,B34) -> 1 | F34: =countif('Check in'!B:B,B34) -> 0 | G34: =ifs(exact(E34,F34),"Available",F34>E34,"Check item out first",E34>F34,"Checked out") -> Checked out | H34: =Inventory!B:B -> SMS gateway
A35: 44727.437 | B35: 0441 | C35: Laptop, Dell | D35: Nthabiseng Thakhisi | E35: =countif(B:B,B35) -> 2 | F35: =countif('Check in'!B:B,B35) -> 1 | G35: =ifs(exact(E35,F35),"Available",F35>E35,"Check item out first",E35>F35,"Checked out") -> Checked out | H35: =Inventory!B:B -> Dev & Test Phone
A36: 44727.441 | B36: AD-1 | C36: Switch, HiLook | D36: Finance office | E36: =countif(B:B,B36) -> 1 | F36: =countif('Check in'!B:B,B36) -> 0 | G36: =ifs(exact(E36,F36),"Available",F36>E36,"Check item out first",E36>F36,"Checked out") -> Checked out | H36: =Inventory!B:B -> Makebe Field Site 0363
A37: 44727.446 | B37: AD-2 | C37: Router, ZTE | D37: Finance office | E37: =countif(B:B,B37) -> 1 | F37: =countif('Check in'!B:B,B37) -> 0 | G37: =ifs(exact(E37,F37),"Available",F37>E37,"Check item out first",E37>F37,"Checked out") -> Checked out | H37: =Inventory!B:B -> Survey Phone 0369
A38: 44727.446 | B38: AD-3 | C38: Phone,iServe | D38: Finance office | E38: =countif(B:B,B38) -> 1 | F38: =countif('Check in'!B:B,B38) -> 0 | G38: =ifs(exact(E38,F38),"Available",F38>E38,"Check item out first",E38>F38,"Checked out") -> Checked out | H38: =Inventory!B:B -> Survey Phone 0370
A39: 44727.651 | B39: RET 04 | C39: Hp Laptop,Charger | D39: Lichaba West | E39: 2 | F39: =countif('Check in'!B:B,B39) -> 2 | G39: =ifs(exact(E39,F39),"Available",F39>E39,"Check item out first",E39>F39,"Checked out") -> Available | H39: =Inventory!B:B -> Pajero
A40: 44810.611 | B40: Untagged/None | C40: Power Bank | D40: Tumisang Mathaba | E40: 2 | F40: =countif('Check in'!B:B,B40) -> 0 | G40: =ifs(exact(E40,F40),"Available",F40>E40,"Check item out first",E40>F40,"Checked out") -> Checked out | H40: =Inventory!B:B -> Surf -2 0373
A41: 44810.615 | B41: MOD0009 | C41: Kuwi Router. No additional accessories | D41: Lichaba West | E41: 2 | F41: =countif('Check in'!B:B,B41) -> 0 | G41: =ifs(exact(E41,F41),"Available",F41>E41,"Check item out first",E41>F41,"Checked out") -> Checked out | H41: =Inventory!B:B -> Customer Support
A42: 44810.615 | B42: Untagged/None | C42: Usb Cable | D42: Kekeletso Rakoti | E42: 2 | F42: =countif('Check in'!B:B,B42) -> 0 | G42: =ifs(exact(E42,F42),"Available",F42>E42,"Check item out first",E42>F42,"Checked out") -> Checked out | H42: =Inventory!B:B
A43: 44810.616 | B43: Untagged/None | C43: Power Cable | D43: Sello (Reticulation) | E43: 2 | F43: =countif('Check in'!B:B,B43) -> 0 | G43: =ifs(exact(E43,F43),"Available",F43>E43,"Check item out first",E43>F43,"Checked out") -> Checked out | H43: =Inventory!B:B -> Com 01
A44: 44810.619 | B44: LOG02 | C44: Mouse | D44: Thabo Monoto | E44: 2 | F44: =countif('Check in'!B:B,B44) -> 0 | G44: =ifs(exact(E44,F44),"Available",F44>E44,"Check item out first",E44>F44,"Checked out") -> Checked out | H44: =Inventory!B:B -> Com 02
A45: 44810.62 | B45: KB02 | C45: Keyboard | D45: Thabo Monoto | E45: 2 | F45: =countif('Check in'!B:B,B45) -> 0 | G45: =ifs(exact(E45,F45),"Available",F45>E45,"Check item out first",E45>F45,"Checked out") -> Checked out | H45: =Inventory!B:B -> Com 03
A46: 44810.622 | B46: LOG01 | C46: Mouse | D46: Mojabeng Sonopo | E46: 2 | F46: =countif('Check in'!B:B,B46) -> 0 | G46: =ifs(exact(E46,F46),"Available",F46>E46,"Check item out first",E46>F46,"Checked out") -> Checked out | H46: =Inventory!B:B -> Com 04
A47: 44810.623 | B47: KB01 | C47: Keyboard | D47: Mojabeng Sonopo | E47: 2 | F47: =countif('Check in'!B:B,B47) -> 0 | G47: =ifs(exact(E47,F47),"Available",F47>E47,"Check item out first",E47>F47,"Checked out") -> Checked out | H47: =Inventory!B:B -> Com 05
A48: 44810.624 | B48: CP01 | C48: CPU with Hdmi,dispaly Cable,wifi adapter | D48: Mojabeng Sonopo | E48: 2 | F48: =countif('Check in'!B:B,B48) -> 0 | G48: =ifs(exact(E48,F48),"Available",F48>E48,"Check item out first",E48>F48,"Checked out") -> Checked out | H48: =Inventory!B:B -> Com 06
A49: 44810.625 | B49: CHR01 | C49: Charger | D49: Mojabeng Sonopo | E49: 2 | F49: =countif('Check in'!B:B,B49) -> 0 | G49: =ifs(exact(E49,F49),"Available",F49>E49,"Check item out first",E49>F49,"Checked out") -> Checked out | H49: =Inventory!B:B -> Com 07
A50: 44812.59 | B50: Untagged/None | C50: Power Cable | D50: Mamoritsoane Tlaba | E50: 2 | F50: =countif('Check in'!B:B,B50) -> 0 | G50: =ifs(exact(E50,F50),"Available",F50>E50,"Check item out first",E50>F50,"Checked out") -> Checked out
B52: Surf -1 | C52: Phone | E52: =countif(B:B,B52) -> 1 | F52: =countif('Check in'!B:B,B52) -> 1 | G52: =ifs(exact(E52,F52),"Available",F52>E52,"Check item out first",E52>F52,"Checked out") -> Available
B53: X-trail Phone | C53: Phone | E53: =countif(B:B,B53) -> 1 | F53: =countif('Check in'!B:B,B53) -> 1 | G53: =ifs(exact(E53,F53),"Available",F53>E53,"Check item out first",E53>F53,"Checked out") -> Available
B54: Truck 36 Phone | C54: Phone | E54: =countif(B:B,B54) -> 1 | F54: =countif('Check in'!B:B,B54) -> 1 | G54: =ifs(exact(E54,F54),"Available",F54>E54,"Check item out first",E54>F54,"Checked out") -> Available
B55: SMS gateway | C55: Phone | E55: =countif(B:B,B55) -> 1 | F55: =countif('Check in'!B:B,B55) -> 2 | G55: =ifs(exact(E55,F55),"Available",F55>E55,"Check item out first",E55>F55,"Checked out") -> Check item out first
B56: Dev & Test Phone | C56: Phone | E56: =countif(B:B,B56) -> 1 | F56: =countif('Check in'!B:B,B56) -> 2 | G56: =ifs(exact(E56,F56),"Available",F56>E56,"Check item out first",E56>F56,"Checked out") -> Check item out first
B57: Makebe Field Site 0363 | C57: Phone | D57: EE | E57: =countif(B:B,B57) -> 1 | F57: =countif('Check in'!B:B,B57) -> 1 | G57: =ifs(exact(E57,F57),"Available",F57>E57,"Check item out first",E57>F57,"Checked out") -> Available
B58: Survey Phone 0369 | C58: Phone | E58: =countif(B:B,B58) -> 1 | F58: =countif('Check in'!B:B,B58) -> 1 | G58: =ifs(exact(E58,F58),"Available",F58>E58,"Check item out first",E58>F58,"Checked out") -> Available
B59: Survey Phone 0370 | C59: Phone | E59: =countif(B:B,B59) -> 1 | F59: =countif('Check in'!B:B,B59) -> 1 | G59: =ifs(exact(E59,F59),"Available",F59>E59,"Check item out first",E59>F59,"Checked out") -> Available
B60: Pajero | C60: Phone | E60: =countif(B:B,B60) -> 1 | F60: =countif('Check in'!B:B,B60) -> 2 | G60: =ifs(exact(E60,F60),"Available",F60>E60,"Check item out first",E60>F60,"Checked out") -> Check item out first
B61: Surf -2 0373 | C61: Phone | E61: =countif(B:B,B61) -> 1 | F61: =countif('Check in'!B:B,B61) -> 1 | G61: =ifs(exact(E61,F61),"Available",F61>E61,"Check item out first",E61>F61,"Checked out") -> Available
B62: Customer Support | C62: Phone | E62: =countif(B:B,B62) -> 1 | F62: =countif('Check in'!B:B,B62) -> 1 | G62: =ifs(exact(E62,F62),"Available",F62>E62,"Check item out first",E62>F62,"Checked out") -> Available
B63: Com 04 | C63: Committee Phone | D63: Tumelo Makhakhe | E63: =countif(B:B,B63) -> 1 | F63: =countif('Check in'!B:B,B63) -> 0 | G63: =ifs(exact(E63,F63),"Available",F63>E63,"Check item out first",E63>F63,"Checked out") -> Checked out
B64: Com 05 | C64: Committee Phone | D64: Tumelo Makhakhe | E64: =countif(B:B,B64) -> 1 | F64: =countif('Check in'!B:B,B64) -> 0 | G64: =ifs(exact(E64,F64),"Available",F64>E64,"Check item out first",E64>F64,"Checked out") -> Checked out
B65: Com 06 | C65: Committee Phone | D65: Tumelo Makhakhe | E65: =countif(B:B,B65) -> 1 | F65: =countif('Check in'!B:B,B65) -> 0 | G65: =ifs(exact(E65,F65),"Available",F65>E65,"Check item out first",E65>F65,"Checked out") -> Checked out
B66: Com 07 | C66: Committee Phone | D66: Tumelo Makhakhe | E66: =countif(B:B,B66) -> 1 | F66: =countif('Check in'!B:B,B66) -> 0 | G66: =ifs(exact(E66,F66),"Available",F66>E66,"Check item out first",E66>F66,"Checked out") -> Checked out
B67: Com 08 | C67: Committee Phone | D67: Tumelo Makhakhe | E67: =countif(B:B,B67) -> 1 | F67: =countif('Check in'!B:B,B67) -> 0 | G67: =ifs(exact(E67,F67),"Available",F67>E67,"Check item out first",E67>F67,"Checked out") -> Checked out
B68: Com 09 | C68: Committee Phone | D68: Tumelo Makhakhe | E68: =countif(B:B,B68) -> 1 | F68: =countif('Check in'!B:B,B68) -> 0 | G68: =ifs(exact(E68,F68),"Available",F68>E68,"Check item out first",E68>F68,"Checked out") -> Checked out
B69: Com 10 | C69: Committee Phone | D69: Tumelo Makhakhe | E69: =countif(B:B,B69) -> 1 | F69: =countif('Check in'!B:B,B69) -> 0 | G69: =ifs(exact(E69,F69),"Available",F69>E69,"Check item out first",E69>F69,"Checked out") -> Checked out
B70: Com 11 | C70: Committee Phone | D70: Tumelo Makhakhe | E70: =countif(B:B,B70) -> 1 | F70: =countif('Check in'!B:B,B70) -> 0 | G70: =ifs(exact(E70,F70),"Available",F70>E70,"Check item out first",E70>F70,"Checked out") -> Checked out
B71: Com 12 | C71: Committee Phone | D71: Tumelo Makhakhe | E71: =countif(B:B,B71) -> 1 | F71: =countif('Check in'!B:B,B71) -> 0 | G71: =ifs(exact(E71,F71),"Available",F71>E71,"Check item out first",E71>F71,"Checked out") -> Checked out
B72: Com 13 | C72: Committee Phone | D72: Tumelo Makhakhe | E72: =countif(B:B,B72) -> 1 | F72: =countif('Check in'!B:B,B72) -> 0 | G72: =ifs(exact(E72,F72),"Available",F72>E72,"Check item out first",E72>F72,"Checked out") -> Checked out
B73: Com 14 | C73: Committee Phone | D73: Tumelo Makhakhe | E73: =countif(B:B,B73) -> 1 | F73: =countif('Check in'!B:B,B73) -> 0 | G73: =ifs(exact(E73,F73),"Available",F73>E73,"Check item out first",E73>F73,"Checked out") -> Checked out
B74: Com 15 | C74: Committee Phone | D74: Tumelo Makhakhe | E74: =countif(B:B,B74) -> 1 | F74: =countif('Check in'!B:B,B74) -> 0 | G74: =ifs(exact(E74,F74),"Available",F74>E74,"Check item out first",E74>F74,"Checked out") -> Checked out
... B102: Com 45 | C102: Committee Phone | D102: Tumelo Makhakhe | E102: =countif(B:B,B102) -> 1 | F102: =countif('Check in'!B:B,B102) -> 0 | G102: =ifs(exact(E102,F102),"Available",F102>E102,"Check item out first",E102>F102,"Checked out") -> Checked out
B103: 006 | E103: =countif(B:B,B103) -> 1 | F103: =countif('Check in'!B:B,B103) -> 1 | G103: =ifs(exact(E103,F103),"Available",F103>E103,"Check item out first",E103>F103,"Checked out") -> Available
B104: 009 | E104: =countif(B:B,B104) -> 1 | F104: =countif('Check in'!B:B,B104) -> 1 | G104: =ifs(exact(E104,F104),"Available",F104>E104,"Check item out first",E104>F104,"Checked out") -> Available
B105: 008 | E105: =countif(B:B,B105) -> 1 | F105: =countif('Check in'!B:B,B105) -> 1 | G105: =ifs(exact(E105,F105),"Available",F105>E105,"Check item out first",E105>F105,"Checked out") -> Available
B106: 0365 | E106: =countif(B:B,B106) -> 1 | F106: =countif('Check in'!B:B,B106) -> 1 | G106: =ifs(exact(E106,F106),"Available",F106>E106,"Check item out first",E106>F106,"Checked out") -> Available
B107: ADM01 | E107: =countif(B:B,B107) -> 1 | F107: =countif('Check in'!B:B,B107) -> 0 | G107: =ifs(exact(E107,F107),"Available",F107>E107,"Check item out first",E107>F107,"Checked out") -> Checked out
B109: New02 | E109: =countif(B:B,B109) -> 1 | F109: =countif('Check in'!B:B,B109) -> 1 | G109: =ifs(exact(E109,F109),"Available",F109>E109,"Check item out first",E109>F109,"Checked out") -> Available
B110: RET 01 | C110: Hp Laptop | E110: =countif(B:B,B110) -> 1 | F110: =countif('Check in'!B:B,B110) -> 1 | G110: =ifs(exact(E110,F110),"Available",F110>E110,"Check item out first",E110>F110,"Checked out") -> Available
B111: RET 02 | C111: Hp Laptop | E111: =countif(B:B,B111) -> 1 | F111: =countif('Check in'!B:B,B111) -> 1 | G111: =ifs(exact(E111,F111),"Available",F111>E111,"Check item out first",E111>F111,"Checked out") -> Available
B112: RET 03 | C112: Hp Laptop | E112: =countif(B:B,B112) -> 1 | F112: =countif('Check in'!B:B,B112) -> 1 | G112: =ifs(exact(E112,F112),"Available",F112>E112,"Check item out first",E112>F112,"Checked out") -> Available
B114: RET 05 | C114: Hp Laptop | E114: =countif(B:B,B114) -> 1 | F114: =countif('Check in'!B:B,B114) -> 1 | G114: =ifs(exact(E114,F114),"Available",F114>E114,"Check item out first",E114>F114,"Checked out") -> Available
B115: RET 06 | C115: Hp Laptop | E115: =countif(B:B,B115) -> 1 | F115: =countif('Check in'!B:B,B115) -> 1 | G115: =ifs(exact(E115,F115),"Available",F115>E115,"Check item out first",E115>F115,"Checked out") -> Available
B116: RET 07 | C116: Hp Laptop | E116: =countif(B:B,B116) -> 1 | F116: =countif('Check in'!B:B,B116) -> 1 | G116: =ifs(exact(E116,F116),"Available",F116>E116,"Check item out first",E116>F116,"Checked out") -> Available
B117: RET 08 | C117: Hp Laptop | E117: =countif(B:B,B117) -> 1 | F117: =countif('Check in'!B:B,B117) -> 1 | G117: =ifs(exact(E117,F117),"Available",F117>E117,"Check item out first",E117>F117,"Checked out") -> Available
B118: RET 09 | C118: Hp Laptop | E118: =countif(B:B,B118) -> 1 | F118: =countif('Check in'!B:B,B118) -> 1 | G118: =ifs(exact(E118,F118),"Available",F118>E118,"Check item out first",E118>F118,"Checked out") -> Available
B119: RET 10 | C119: Hp Laptop | E119: =countif(B:B,B119) -> 1 | F119: =countif('Check in'!B:B,B119) -> 1 | G119: =ifs(exact(E119,F119),"Available",F119>E119,"Check item out first",E119>F119,"Checked out") -> Available
B123: 0444 | E123: =countif(B:B,B123) -> 2 | F123: =countif('Check in'!B:B,B123) -> 1 | G123: =ifs(exact(E123,F123),"Available",F123>E123,"Check item out first",E123>F123,"Checked out") -> Checked out
B124: 0420 | E124: =countif(B:B,B124) -> 2 | F124: 1 | G124: =ifs(exact(E124,F124),"Available",F124>E124,"Check item out first",E124>F124,"Checked out") -> Checked out
B125: 0381-B | E125: =countif(B:B,B125) -> 2 | F125: =countif('Check in'!B:B,B125) -> 1 | G125: =ifs(exact(E125,F125),"Available",F125>E125,"Check item out first",E125>F125,"Checked out") -> Checked out
B127: 0441 | E127: =countif(B:B,B127) -> 2 | F127: =countif('Check in'!B:B,B127) -> 1 | G127: =ifs(exact(E127,F127),"Available",F127>E127,"Check item out first",E127>F127,"Checked out") -> Checked out
B128: 0111 | E128: =countif(B:B,B128) -> 1 | F128: =countif('Check in'!B:B,B128) -> 1 | G128: =ifs(exact(E128,F128),"Available",F128>E128,"Check item out first",E128>F128,"Checked out") -> Available
B129: 0105 | E129: =countif(B:B,B129) -> 2 | F129: =countif('Check in'!B:B,B129) -> 2 | G129: =ifs(exact(E129,F129),"Available",F129>E129,"Check item out first",E129>F129,"Checked out") -> Available
B130: 0140 | E130: =countif(B:B,B130) -> 1 | F130: =countif('Check in'!B:B,B130) -> 1 | G130: =ifs(exact(E130,F130),"Available",F130>E130,"Check item out first",E130>F130,"Checked out") -> Available
B131: 0142 | E131: =countif(B:B,B131) -> 1 | F131: =countif('Check in'!B:B,B131) -> 1 | G131: =ifs(exact(E131,F131),"Available",F131>E131,"Check item out first",E131>F131,"Checked out") -> Available
B132: 0149 | E132: =countif(B:B,B132) -> 1 | F132: =countif('Check in'!B:B,B132) -> 1 | G132: =ifs(exact(E132,F132),"Available",F132>E132,"Check item out first",E132>F132,"Checked out") -> Available
B133: 0100 | E133: =countif(B:B,B133) -> 2 | F133: =countif('Check in'!B:B,B133) -> 2 | G133: =ifs(exact(E133,F133),"Available",F133>E133,"Check item out first",E133>F133,"Checked out") -> Available
B134: 0091 | E134: =countif(B:B,B134) -> 2 | F134: =countif('Check in'!B:B,B134) -> 2 | G134: =ifs(exact(E134,F134),"Available",F134>E134,"Check item out first",E134>F134,"Checked out") -> Available
...

Sheet Check in
A1: Timestamp | B1: Company ID | C1: Returned by | D1: Condition
A3: 44725.697 | B3: Surf -1 | C3: test
A4: 44726.368 | B4: Main 0374 | C4: Tumelo
A6: 44728.404 | B6: Truck 36 Phone | C6: Tlhokomelo
A7: 44728.458 | B7: SMS gateway | C7: testing | D7: Needs Maintainance
A8: 44728.536 | B8: X-trail Phone | C8: testing | D8: Good Condition
A9: 44728.536 | B9: Dev & Test Phone | C9: testing | D9: Needs Repair
A10: 44728.537 | B10: Pajero | C10: testing | D10: Unrepairable
A11: 44729.628 | B11: RET 04 | C11: Lichaba West | D11: Good Condition
A12: 44812.631 | C12: Kekeletso Rakoti | D12: Good Condition
B13: SMS gateway
B14: Dev & Test Phone
B15: Makebe Field Site 0363
B16: Survey Phone 0369
B17: Survey Phone 0370
B18: Pajero
B19: Surf -2 0373
B20: Customer Support
B21: Com 01 | C21: test | D21: good condition
B22: MOD0001 | C22: Matete | D22: good condition
B23: MODUSB0002 | C23: Matete | D23: good condition
B45: Com 25
B66: 006
B67: 009
B70: 008
B71: 0365
B74: New02
B80: RET 01
B81: RET 02
B82: RET 03
B83: RET 04
B84: RET 05
B85: RET 06
... B187: RET0023

Sheet Waste
A1: Item | B1: Quantity
A2: Tablets | B2: 5
A3: Laptop Battery | B3: 1
A4: Phone Battery | B4: 1

Sheet Total
A1: Available | D1: EE | E1: HR | F1: Finance | G1: O&M | H1: EHS | I1: Procurement | J1: Production | K1: Fleet | L1: Project Management | M1: Reticulation | N1: Pueco
A2: Laptops | B2: =COUNTIF(Inventory!E:E,"Laptop") -> 27 | D2: =COUNTIFS(Inventory!E:E,"Laptop",Inventory!M:M,"EE") -> 6 | E2: =COUNTIFS(Inventory!E:E,"Laptop",Inventory!M:M,"Human Resources") -> 0 | F2: =COUNTIFS(Inventory!E:E,"Laptop",Inventory!M:M,"Finance") -> 1 | G2: =COUNTIFS(Inventory!E:E,"Laptop",Inventory!M:M,"Operations and Maintenance") -> 0 | H2: =COUNTIFS(Inventory!E:E,"Laptop",Inventory!M:M,"EHS") -> 1 | I2: =COUNTIFS(Inventory!E:E,"Laptop",Inventory!M:M,"Procurement") -> 0 | J2: =COUNTIFS(Inventory!E:E,"Laptop",Inventory!M:M,"Production") -> 0 | K2: 1 | L2: =COUNTIFS(Inventory!E:E,"Laptop",Inventory!M:M,"Project Management") -> 3 | M2: =COUNTIFS(Inventory!E:E,"Laptop",Inventory!M:M,"Reticulation") -> 10 | N2: =COUNTIFS(Inventory!E:E,"Laptop",Inventory!M:M,"Pueco") -> 0
A3: Phones | B3: =COUNTIF(Inventory!E:E,"Phone") -> 59 | D3: =COUNTIFS(Inventory!E:E,"Phone",Inventory!M:M,"EE") -> 0 | E3: =COUNTIFS(Inventory!E:E,"Phone",Inventory!M:M,"Human Resources") -> 0 | F3: =COUNTIFS(Inventory!E:E,"Phone",Inventory!M:M,"Finance") -> 0 | G3: =COUNTIFS(Inventory!E:E,"Phone",Inventory!M:M,"Operations and Maintenance") -> 0 | H3: =COUNTIFS(Inventory!E:E,"Phone",Inventory!M:M,"EHS") -> 1 | I3: =COUNTIFS(Inventory!E:E,"Phone",Inventory!M:M,"Procurement") -> 1 | J3: =COUNTIFS(Inventory!E:E,"Phone",Inventory!M:M,"Production") -> 0 | K3: 1 | L3: =COUNTIFS(Inventory!E:E,"Phone",Inventory!M:M,"Project Management") -> 42 | M3: =COUNTIFS(Inventory!E:E,"Phone",Inventory!M:M,"Reticulation") -> 2 | N3: =COUNTIFS(Inventory!E:E,"Phone",Inventory!M:M,"Pueco") -> 0
A4: Desktops | B4: =COUNTIF(Inventory!E:E,"Monitor") -> 20 | D4: =COUNTIFS(Inventory!E:E,"Monitor",Inventory!M:M,"EE") -> 7 | E4: =COUNTIFS(Inventory!E:E,"Monitor",Inventory!M:M,"Human Resources") -> 0 | F4: =COUNTIFS(Inventory!E:E,"Monitor",Inventory!M:M,"Finance") -> 4 | G4: =COUNTIFS(Inventory!E:E,"Monitor",Inventory!M:M,"Operations and Maintenance") -> 2 | H4: =COUNTIFS(Inventory!E:E,"Monitor",Inventory!M:M,"EHS") -> 1 | I4: =COUNTIFS(Inventory!E:E,"Monitor",Inventory!M:M,"Procurement") -> 2 | J4: =COUNTIFS(Inventory!E:E,"Monitor",Inventory!M:M,"Production") -> 0 | K4: =COUNTIFS(Inventory!E:E,"Monitor",Inventory!M:M,"Fleet") -> 0 | L4: =COUNTIFS(Inventory!E:E,"Monitor",Inventory!M:M,"Project Management") -> 2 | M4: =COUNTIFS(Inventory!E:E,"Monitor",Inventory!M:M,"Reticulation") -> 0 | N4: =COUNTIFS(Inventory!E:E,"Monitor",Inventory!M:M,"Pueco") -> 0
A5: Tablets | B5: =COUNTIF(Inventory!E:E,"Tablet") -> 13 | D5: =COUNTIFS(Inventory!E:E,"Tablet",Inventory!M:M,"EE") -> 1 | E5: =COUNTIFS(Inventory!E:E,"Tablet",Inventory!M:M,"Human Resources") -> 0 | F5: =COUNTIFS(Inventory!E:E,"Tablet",Inventory!M:M,"Finance") -> 0 | G5: =COUNTIFS(Inventory!E:E,"Tablet",Inventory!M:M,"Operations and Maintenance") -> 0 | H5: =COUNTIFS(Inventory!E:E,"Tablet",Inventory!M:M,"EHS") -> 12 | I5: =COUNTIFS(Inventory!E:E,"Tablet",Inventory!M:M,"Procurement") -> 0 | J5: =COUNTIFS(Inventory!E:E,"Tablet",Inventory!M:M,"Production") -> 0 | K5: =COUNTIFS(Inventory!E:E,"Tablet",Inventory!M:M,"Fleet") -> 0 | L5: =COUNTIFS(Inventory!E:E,"Tablet",Inventory!M:M,"Project Management") -> 0 | M5: =COUNTIFS(Inventory!E:E,"Tablet",Inventory!M:M,"Reticulation") -> 0 | N5: =COUNTIFS(Inventory!E:E,"Tablet",Inventory!M:M,"Pueco") -> 0
A6: Other | B6: =countifs(Inventory!E:E,"<>" &Inventory!E100,Inventory!E:E,"<>" &Inventory!E30,Inventory!E:E,"<>" &Inventory!E118,Inventory!E:E,"<>" &Inventory!E170) -> 1066 | D6: =countifs(Inventory!E:E,"<>" &Inventory!E100,Inventory!E:E,"<>" &Inventory!E30,Inventory!E:E,"<>" &Inventory!E118,Inventory!E:E,"<>" &Inventory!E170,Inventory!E:E,"<>" &Inventory!E217,Inventory!M:M,"EE") -> 99 | E6: =countifs(Inventory!E:E,"<>" &Inventory!E100,Inventory!E:E,"<>" &Inventory!E30,Inventory!E:E,"<>" &Inventory!E118,Inventory!E:E,"<>" &Inventory!E170,Inventory!E:E,"<>" &Inventory!E217,Inventory!M:M,"Human Resources") -> 0 | F6: =countifs(Inventory!E:E,"<>" &Inventory!E100,Inventory!E:E,"<>" &Inventory!E30,Inventory!E:E,"<>" &Inventory!E118,Inventory!E:E,"<>" &Inventory!E170,Inventory!E:E,"<>" &Inventory!E217,Inventory!M:M,"Finance") -> 3 | G6: =countifs(Inventory!E:E,"<>" &Inventory!E100,Inventory!E:E,"<>" &Inventory!E30,Inventory!E:E,"<>" &Inventory!E118,Inventory!E:E,"<>" &Inventory!E170,Inventory!E:E,"<>" &Inventory!E217,Inventory!M:M,"Operations and Maintenance") -> 1 | H6: =countifs(Inventory!E:E,"<>" &Inventory!E100,Inventory!E:E,"<>" &Inventory!E30,Inventory!E:E,"<>" &Inventory!E118,Inventory!E:E,"<>" &Inventory!E170,Inventory!E:E,"<>" &Inventory!E217,Inventory!M:M,"EHS") -> 0 | I6: =countifs(Inventory!E:E,"<>" &Inventory!E100,Inventory!E:E,"<>" &Inventory!E30,Inventory!E:E,"<>" &Inventory!E118,Inventory!E:E,"<>" &Inventory!E170,Inventory!E:E,"<>" &Inventory!E217,Inventory!M:M,"Procurement") -> 2 | J6: =countifs(Inventory!E:E,"<>" &Inventory!E100,Inventory!E:E,"<>" &Inventory!E30,Inventory!E:E,"<>" &Inventory!E118,Inventory!E:E,"<>" &Inventory!E170,Inventory!M:M,"Production") -> 0 | K6: =countifs(Inventory!E:E,"<>" &Inventory!E100,Inventory!E:E,"<>" &Inventory!E30,Inventory!E:E,"<>" &Inventory!E118,Inventory!E:E,"<>" &Inventory!E170,Inventory!E:E,"<>" &Inventory!E217,Inventory!M:M,"Fleet") -> 4 | L6: =countifs(Inventory!E:E,"<>" &Inventory!E100,Inventory!E:E,"<>" &Inventory!E30,Inventory!E:E,"<>" &Inventory!E118,Inventory!E:E,"<>" &Inventory!E170,Inventory!E:E,"<>" &Inventory!E217,Inventory!M:M,"Project Management") -> 2 | M6: =countifs(Inventory!E:E,"<>" &Inventory!E100,Inventory!E:E,"<>" &Inventory!E30,Inventory!E:E,"<>" &Inventory!E118,Inventory!E:E,"<>" &Inventory!E170,Inventory!E:E,"<>" &Inventory!E217,Inventory!M:M,"Reticulation") -> 0 | N6: =countifs(Inventory!E:E,"<>" &Inventory!E100,Inventory!E:E,"<>" &Inventory!E30,Inventory!E:E,"<>" &Inventory!E118,Inventory!E:E,"<>" &Inventory!E170,Inventory!E:E,"<>" &Inventory!E217,Inventory!M:M,"Pueco") -> 1
A7: TOTAL | B7: =SUM(B2:B6) -> 1185
A9: Request
A10: Laptops | B10: =COUNTIF(Tickets!J:J,"Laptop") -> 29 | D10: 0 | E10: =COUNTIFs(Tickets!J:J,"Laptop",Tickets!D:D,"Human Resources") -> 0 | F10: =COUNTIFS(Tickets!J:J,"Laptop",Tickets!D:D,"Finance") -> 1 | G10: 0 | H10: =COUNTIFS(Tickets!J:J,"Laptop",Tickets!D:D,"EHS") -> 2 | I10: =COUNTIFs(Tickets!J:J,"Laptop",Tickets!D:D,"Procurement") -> 0 | J10: =COUNTIFS(Tickets!J:J,"Laptop",Tickets!D:D,"Production") -> 1 | K10: =COUNTIFS(Tickets!J:J,"Laptop",Tickets!D:D,"Fleet") -> 1 | L10: =COUNTIFS(Tickets!J:J,"Laptop",Tickets!D:D,"Project Management") -> 4 | M10: =COUNTIFS(Tickets!J:J,"Laptop",Tickets!D:D,"Reticulation") -> 9 | N10: =COUNTIFS(Tickets!J:J,"Laptop",Tickets!D:D,"Pueco") -> 0
A11: Phones | B11: =COUNTIF(Tickets!J:J,"Phone") -> 23 | D11: =COUNTIFS(Tickets!J:J,"Phone",Tickets!D:D,"EE") -> 2 | E11: =COUNTIFs(Tickets!J:J,"Phone",Tickets!D:D,"Human Resources") -> 0 | F11: =COUNTIFS(Tickets!J:J,"Phone",Tickets!D:D,"Finance") -> 0 | G11: =COUNTIFS(Tickets!J:J,"Phone",Tickets!D:D,"Operations and Maintenance") -> 3 | H11: =COUNTIFS(Tickets!J:J,"Phone",Tickets!D:D,"EHS") -> 0 | I11: =COUNTIFs(Tickets!J:J,"Phone",Tickets!D:D,"Procurement") -> 1 | J11: =COUNTIFS(Tickets!J:J,"Phone",Tickets!D:D,"Production") -> 0 | K11: =COUNTIFS(Tickets!J:J,"Phone",Tickets!D:D,"Fleet") -> 1 | L11: =COUNTIFS(Tickets!J:J,"Phone",Tickets!D:D,"Project Management") -> 3 | M11: =COUNTIFS(Tickets!J:J,"Phone",Tickets!D:D,"Reticulation") -> 11 | N11: =COUNTIFS(Tickets!J:J,"Phone",Tickets!D:D,"Pueco") -> 0
A12: Monitor | B12: =COUNTIF(Tickets!J:J,"Monitor") -> 13 | D12: =COUNTIFS(Tickets!J:J,"Monitor",Tickets!D:D,"EE") -> 3 | E12: =COUNTIFs(Tickets!J:J,"Monitor",Tickets!D:D,"Human Resources") -> 0 | F12: =COUNTIFS(Tickets!J:J,"Monitor",Tickets!D:D,"Finance") -> 0 | G12: =COUNTIFS(Tickets!J:J,"Monitor",Tickets!D:D,"Operations and Maintenance") -> 2 | H12: =COUNTIFS(Tickets!J:J,"Monitor",Tickets!D:D,"EHS") -> 1 | I12: =COUNTIFs(Tickets!J:J,"Monitor",Tickets!D:D,"Procurement") -> 1 | J12: =COUNTIFS(Tickets!J:J,"Monitor",Tickets!D:D,"Production") -> 0 | K12: =COUNTIFS(Tickets!J:J,"Monitor",Tickets!D:D,"Fleet") -> 0 | L12: =COUNTIFS(Tickets!J:J,"Monitor",Tickets!D:D,"Project Management") -> 2 | M12: =COUNTIFS(Tickets!J:J,"Monitor",Tickets!D:D,"Reticulation") -> 1 | N12: =COUNTIFS(Tickets!J:J,"Monitor",Tickets!D:D,"Pueco") -> 1
A13: Tablets | B13: =COUNTIF(Tickets!J:J,"Tablet") -> 4 | D13: =COUNTIFS(Tickets!J:J,"Tablet",Tickets!D:D,"EE") -> 1 | E13: =COUNTIFs(Tickets!J:J,"Tablet",Tickets!D:D,"Human Resources") -> 0 | F13: =COUNTIFS(Tickets!J:J,"Tablet",Tickets!D:D,"Finance") -> 0 | G13: =COUNTIFS(Tickets!J:J,"Tablet",Tickets!D:D,"Operations and Maintenance") -> 0 | H13: =COUNTIFS(Tickets!J:J,"Tablet",Tickets!D:D,"EHS") -> 1 | I13: =COUNTIFs(Tickets!J:J,"Tablet",Tickets!D:D,"Procurement") -> 0 | J13: =COUNTIFS(Tickets!J:J,"Tablet",Tickets!D:D,"Production") -> 0 | K13: =COUNTIFS(Tickets!J:J,"Tablet",Tickets!D:D,"Fleet") -> 0 | L13: =COUNTIFS(Tickets!J:J,"Tablet",Tickets!D:D,"Project Management") -> 1 | M13: =COUNTIFS(Tickets!J:J,"Tablet",Tickets!D:D,"Reticulation") -> 0 | N13: =COUNTIFS(Tickets!J:J,"Tablet",Tickets!D:D,"Pueco") -> 0
A14: Other | B14: =countifs(Tickets!J:J,"<>" &"Laptop",Tickets!J:J,"<>" &"Phone",Tickets!J:J,"<>" &"Monitor",Tickets!J:J,"<>" &"") -> 223
A15: TOTAL | B15: =SUM(B10:B14) -> 292

Sheet Dropdown
A1: Usable
A2: Not Usable
A3: in maintanace
